{"assets":{"F53BF4CCEC422DA7C11AC9737828F37B":{"type":"texture","index":4,"url":{"native":"assets\/386DC167-CB3E-4FB7-A2BB-E50C8FA1DF09.pdf"},"width":427,"height":38},"9BD4D1AA1ECF6CB5EDB3E73F5C0E10B4":{"type":"texture","index":3,"url":{"native":"assets\/386DC167-CB3E-4FB7-A2BB-E50C8FA1DF09.pdf"},"width":80,"height":21},"C54F8979F117F59627802EC083318BDC":{"type":"texture","index":1,"url":{"native":"assets\/386DC167-CB3E-4FB7-A2BB-E50C8FA1DF09.pdf"},"width":4,"height":72},"A37863128BCF3FDA3869001B69046A9A":{"type":"texture","index":6,"url":{"native":"assets\/386DC167-CB3E-4FB7-A2BB-E50C8FA1DF09.pdf"},"width":412,"height":119},"EA5059272FA6B0B485E2B01493C2E69C":{"type":"texture","index":10,"url":{"native":"assets\/386DC167-CB3E-4FB7-A2BB-E50C8FA1DF09.pdf"},"width":960,"height":540},"ED77A4173F60787A84F36B76E1B1DDF4":{"type":"texture","index":8,"url":{"native":"assets\/386DC167-CB3E-4FB7-A2BB-E50C8FA1DF09.pdf"},"width":318,"height":60},"AD08A39BDFC84D2E30FAF14B27AD06B8":{"type":"texture","index":5,"url":{"native":"assets\/386DC167-CB3E-4FB7-A2BB-E50C8FA1DF09.pdf"},"width":319,"height":170},"376E86731AE1B52F73AC6D82B256BB51":{"type":"texture","index":11,"url":{"native":"assets\/386DC167-CB3E-4FB7-A2BB-E50C8FA1DF09.pdf"},"width":960,"height":540},"0C9392F1606516E5FD8AADE86409C03B":{"type":"texture","index":9,"url":{"native":"assets\/386DC167-CB3E-4FB7-A2BB-E50C8FA1DF09.pdf"},"width":156,"height":98},"063F32FE31288BDCCDA81E55EF79D28B":{"type":"texture","index":0,"url":{"native":"assets\/386DC167-CB3E-4FB7-A2BB-E50C8FA1DF09.pdf"},"width":960,"height":540},"BE0EF8AC4767274F13F1A56A0F350673":{"type":"texture","index":7,"url":{"native":"assets\/386DC167-CB3E-4FB7-A2BB-E50C8FA1DF09.pdf"},"width":352,"height":387},"4FC9773900971738E5F56D1D94665F05":{"type":"texture","index":2,"url":{"native":"assets\/386DC167-CB3E-4FB7-A2BB-E50C8FA1DF09.pdf"},"width":4,"height":38}},"events":[{"effects":[{"beginTime":0,"baseLayer":{"animations":[],"initialState":{"affineTransform":[1,0,0,1,0,0],"masksToBounds":false,"rotation":0,"scale":1,"position":{"pointX":249.8005468539117,"pointY":151.78023443447321},"width":318,"sublayerTransform":[1,0,0,0,0,1,0,0,0,0,1,0,0,0,0,1],"contentsRect":{"y":0,"x":0,"width":1,"height":1},"opacity":1,"edgeAntialiasingMask":251658240,"height":60,"hidden":false,"anchorPoint":{"pointX":0.5,"pointY":0.5}},"objectID":"13480192-313A-4D7E-A537-9EBFD811BCE6","layers":[{"animations":[],"initialState":{"affineTransform":[1,0,0,1,0,0],"masksToBounds":false,"rotation":0,"scale":1,"position":{"pointX":389.19945314608833,"pointY":148.21976556552679},"width":318,"sublayerTransform":[1,0,0,0,0,1,0,0,0,0,1,-0.00070015824933551967,0,0,0,1],"contentsRect":{"y":0,"x":0,"width":1,"height":1},"opacity":1,"edgeAntialiasingMask":251658240,"height":60,"hidden":false,"anchorPoint":{"pointX":1.2238976514027935,"pointY":2.4703294260921131}},"layers":[{"animations":[{"additive":false,"timeOffset":0,"beginTime":1e-100,"repeatCount":0,"fillMode":"both","duration":0.001,"autoreverses":false,"animations":[{"additive":false,"timeOffset":0,"beginTime":0,"from":{"scalar":true},"repeatCount":0,"fillMode":"both","duration":0.0001,"autoreverses":false,"property":"hidden","to":{"scalar":false},"removedOnCompletion":true},{"additive":false,"timeOffset":0,"beginTime":0.0001,"from":{"scalar":false},"repeatCount":0,"fillMode":"forwards","duration":0.00089999999999999998,"autoreverses":false,"property":"hidden","to":{"scalar":false},"removedOnCompletion":true}],"removedOnCompletion":false}],"layers":[],"texturedRectangle":{"isBackgroundTexture":true,"singleTextureOpacity":1,"textureType":5,"textBaseline":0,"textXHeight":0,"isVerticalText":false},"initialState":{"affineTransform":[1,0,0,1,0,0],"masksToBounds":false,"rotation":0,"scale":1,"position":{"pointX":157.1994531460883,"pointY":28.219765565526785},"width":318,"sublayerTransform":[1,0,0,0,0,1,0,0,0,0,1,0,0,0,0,1],"contentsRect":{"y":0,"x":0,"width":1,"height":1},"opacity":1,"edgeAntialiasingMask":0,"height":60,"hidden":true,"anchorPoint":{"pointX":0.5,"pointY":0.5}},"texture":"ED77A4173F60787A84F36B76E1B1DDF4"}]}]},"effects":[],"duration":0.001,"type":"buildIn","attributes":{"direction":0},"name":"apple:appear","objectID":"13480192-313A-4D7E-A537-9EBFD811BCE6"}],"automaticPlay":false,"hyperlinks":[],"accessibility":[{"text":"Veeam","targetRectangle":{"y":138.07188846681692,"x":306.32321233957276,"width":59.291999999999973,"height":23}},{"text":"OpenShift\\u2028Virtualization","targetRectangle":{"y":433.87047197613163,"x":87.555826198495311,"width":152.66399999999999,"height":62}},{"text":"Google Shape;4196;p228","targetRectangle":{"y":391.9639363079732,"x":279.04858162131859,"width":145.11181640625,"height":46.586929321289062}},{"text":"Google Shape;1631;p110","targetRectangle":{"y":497.10629293573453,"x":843.40777587890625,"width":76.84375,"height":17.968749999999943}},{"text":"Hundreds of Applications","targetRectangle":{"y":229.01204255930816,"x":188.29054962154714,"width":122.10000000000002,"height":52}},{"text":"6,200 Cores","targetRectangle":{"y":307.01204255930816,"x":189.42054962154717,"width":116.22,"height":26}},{"text":"Google Shape;4194;p228","targetRectangle":{"y":386.26275508383333,"x":15.359758680235245,"width":200.32347106933594,"height":53.941417694091797}},{"text":"Google Shape;4199;p228","targetRectangle":{"y":139.67527516136397,"x":96.273144134796894,"width":121.85031890869141,"height":19.688583374023438}},{"text":"Google Shape;4203;p228","targetRectangle":{"y":4.2256687012140901,"x":499.52881056001388,"width":152.59375,"height":95.250077659522503}},{"text":"Customer Success Story ","targetRectangle":{"y":15.216771233786972,"x":38.398406126367945,"width":429.82900000000001,"height":73.5}}],"baseLayer":{"animations":[],"initialState":{"affineTransform":[1,0,0,1,0,0],"masksToBounds":false,"rotation":0,"scale":1,"position":{"pointX":480,"pointY":270},"width":960,"sublayerTransform":[1,0,0,0,0,1,0,0,0,0,1,0,0,0,0,1],"contentsRect":{"y":0,"x":0,"width":1,"height":1},"opacity":1,"edgeAntialiasingMask":251658240,"height":540,"hidden":false,"anchorPoint":{"pointX":0.5,"pointY":0.5}},"layers":[{"animations":[],"initialState":{"affineTransform":[1,0,0,1,0,0],"masksToBounds":false,"rotation":0,"scale":1,"position":{"pointX":480,"pointY":270},"width":960,"sublayerTransform":[1,0,0,0,0,1,0,0,0,0,1,0,0,0,0,1],"contentsRect":{"y":0,"x":0,"width":1,"height":1},"opacity":1,"edgeAntialiasingMask":251658240,"height":540,"hidden":false,"anchorPoint":{"pointX":0.5,"pointY":0.5}},"layers":[{"animations":[],"initialState":{"affineTransform":[1,0,0,1,0,0],"masksToBounds":false,"rotation":0,"scale":1,"position":{"pointX":480,"pointY":270},"width":960,"sublayerTransform":[1,0,0,0,0,1,0,0,0,0,1,0,0,0,0,1],"contentsRect":{"y":0,"x":0,"width":1,"height":1},"opacity":1,"edgeAntialiasingMask":251658240,"height":540,"hidden":false,"anchorPoint":{"pointX":0.5,"pointY":0.5}},"layers":[{"animations":[],"layers":[],"texturedRectangle":{"isBackgroundTexture":true,"singleTextureOpacity":1,"textureType":1,"textBaseline":0,"textXHeight":0,"isVerticalText":false},"initialState":{"affineTransform":[1,0,0,1,0,0],"masksToBounds":false,"rotation":0,"scale":1,"position":{"pointX":480,"pointY":270},"width":960,"sublayerTransform":[1,0,0,0,0,1,0,0,0,0,1,0,0,0,0,1],"contentsRect":{"y":0,"x":0,"width":1,"height":1},"opacity":1,"edgeAntialiasingMask":0,"height":540,"hidden":false,"anchorPoint":{"pointX":0.5,"pointY":0.5}},"texture":"063F32FE31288BDCCDA81E55EF79D28B"}]}]},{"animations":[],"initialState":{"affineTransform":[1,0,0,1,0,0],"masksToBounds":false,"rotation":0,"scale":1,"position":{"pointX":480,"pointY":270},"width":960,"sublayerTransform":[1,0,0,0,0,1,0,0,0,0,1,0,0,0,0,1],"contentsRect":{"y":0,"x":0,"width":1,"height":1},"opacity":1,"edgeAntialiasingMask":251658240,"height":540,"hidden":false,"anchorPoint":{"pointX":0.5,"pointY":0.5}},"layers":[{"animations":[],"initialState":{"affineTransform":[1,0,0,1,0,0],"masksToBounds":false,"rotation":0,"scale":1,"position":{"pointX":36.982873535156244,"pointY":36.007948083001907},"width":4,"sublayerTransform":[1,0,0,0,0,1,0,0,0,0,1,0,0,0,0,1],"contentsRect":{"y":0,"x":0,"width":1,"height":1},"opacity":1,"edgeAntialiasingMask":251658240,"height":72,"hidden":false,"anchorPoint":{"pointX":0.5,"pointY":0.5}},"layers":[{"animations":[],"layers":[],"texturedRectangle":{"singleTextureOpacity":1,"textXHeight":0,"shapePath":{"lineWidth":1,"flatness":0.59999999999999998,"lineCapStyle":0,"elements":[{"type":"MoveToPoint","points":[[2.3578735351562443,70.811019979132766]]},{"type":"AddLine","points":[[2.3578735351562514,1.0079480830019065]]}],"windingRule":0,"lineJoinStyle":0,"miterLimit":10},"isBackgroundTexture":true,"textBaseline":0,"isVerticalText":false,"textureType":5},"initialState":{"affineTransform":[1,0,0,1,0,0],"masksToBounds":false,"rotation":0,"scale":1,"position":{"pointX":0.017126464843755684,"pointY":34.992051916998093},"width":4,"sublayerTransform":[1,0,0,0,0,1,0,0,0,0,1,0,0,0,0,1],"contentsRect":{"y":0,"x":0,"width":1,"height":1},"opacity":1,"edgeAntialiasingMask":0,"height":72,"hidden":false,"anchorPoint":{"pointX":0.5,"pointY":0.5}},"texture":"C54F8979F117F59627802EC083318BDC"}]}]},{"animations":[],"initialState":{"affineTransform":[1,0,0,1,0,0],"masksToBounds":false,"rotation":0,"scale":1,"position":{"pointX":480,"pointY":270},"width":960,"sublayerTransform":[1,0,0,0,0,1,0,0,0,0,1,0,0,0,0,1],"contentsRect":{"y":0,"x":0,"width":1,"height":1},"opacity":1,"edgeAntialiasingMask":251658240,"height":540,"hidden":false,"anchorPoint":{"pointX":0.5,"pointY":0.5}},"layers":[{"animations":[],"initialState":{"affineTransform":[1,0,0,1,0,0],"masksToBounds":false,"rotation":0,"scale":1,"position":{"pointX":36.982244110107416,"pointY":523.04723928371163},"width":4,"sublayerTransform":[1,0,0,0,0,1,0,0,0,0,1,0,0,0,0,1],"contentsRect":{"y":0,"x":0,"width":1,"height":1},"opacity":1,"edgeAntialiasingMask":251658240,"height":38,"hidden":false,"anchorPoint":{"pointX":0.5,"pointY":0.5}},"layers":[{"animations":[],"layers":[],"texturedRectangle":{"singleTextureOpacity":1,"textXHeight":0,"shapePath":{"lineWidth":1,"flatness":0.59999999999999998,"lineCapStyle":0,"elements":[{"type":"MoveToPoint","points":[[2.3572441101074162,36.999995719729441]]},{"type":"AddLine","points":[[2.3572441101074162,1.0472392837116331]]}],"windingRule":0,"lineJoinStyle":0,"miterLimit":10},"isBackgroundTexture":true,"textBaseline":0,"isVerticalText":false,"textureType":5},"initialState":{"affineTransform":[1,0,0,1,0,0],"masksToBounds":false,"rotation":0,"scale":1,"position":{"pointX":0.017755889892583809,"pointY":17.952760716288367},"width":4,"sublayerTransform":[1,0,0,0,0,1,0,0,0,0,1,0,0,0,0,1],"contentsRect":{"y":0,"x":0,"width":1,"height":1},"opacity":1,"edgeAntialiasingMask":0,"height":38,"hidden":false,"anchorPoint":{"pointX":0.5,"pointY":0.5}},"texture":"4FC9773900971738E5F56D1D94665F05"}]}]},{"animations":[],"initialState":{"affineTransform":[1,0,0,1,0,0],"masksToBounds":false,"rotation":0,"scale":1,"position":{"pointX":480,"pointY":270},"width":960,"sublayerTransform":[1,0,0,0,0,1,0,0,0,0,1,0,0,0,0,1],"contentsRect":{"y":0,"x":0,"width":1,"height":1},"opacity":1,"edgeAntialiasingMask":251658240,"height":540,"hidden":false,"anchorPoint":{"pointX":0.5,"pointY":0.5}},"layers":[{"animations":[],"initialState":{"affineTransform":[1,0,0,1,0,0],"masksToBounds":false,"rotation":0,"scale":1,"position":{"pointX":883.40777587890625,"pointY":507.60629293573453},"width":80,"sublayerTransform":[1,0,0,0,0,1,0,0,0,0,1,0,0,0,0,1],"contentsRect":{"y":0,"x":0,"width":1,"height":1},"opacity":1,"edgeAntialiasingMask":251658240,"height":21,"hidden":false,"anchorPoint":{"pointX":0.5,"pointY":0.5}},"layers":[{"animations":[],"layers":[],"texturedRectangle":{"isBackgroundTexture":true,"singleTextureOpacity":1,"textureType":5,"textBaseline":0,"textXHeight":0,"isVerticalText":false},"initialState":{"affineTransform":[1,0,0,1,0,0],"masksToBounds":false,"rotation":0,"scale":1,"position":{"pointX":38.59222412109375,"pointY":9.3937070642654703},"width":80,"sublayerTransform":[1,0,0,0,0,1,0,0,0,0,1,0,0,0,0,1],"contentsRect":{"y":0,"x":0,"width":1,"height":1},"opacity":1,"edgeAntialiasingMask":0,"height":21,"hidden":false,"anchorPoint":{"pointX":0.5,"pointY":0.5}},"texture":"9BD4D1AA1ECF6CB5EDB3E73F5C0E10B4"}]}]},{"animations":[],"initialState":{"affineTransform":[1,0,0,1,0,0],"masksToBounds":false,"rotation":0,"scale":1,"position":{"pointX":480,"pointY":270},"width":960,"sublayerTransform":[1,0,0,0,0,1,0,0,0,0,1,0,0,0,0,1],"contentsRect":{"y":0,"x":0,"width":1,"height":1},"opacity":1,"edgeAntialiasingMask":251658240,"height":540,"hidden":false,"anchorPoint":{"pointX":0.5,"pointY":0.5}},"layers":[{"animations":[],"initialState":{"affineTransform":[1,0,0,1,0,0],"masksToBounds":false,"rotation":0,"scale":1,"position":{"pointX":242.29998121486892,"pointY":24.618346322287948},"width":427,"sublayerTransform":[1,0,0,0,0,1,0,0,0,0,1,0,0,0,0,1],"contentsRect":{"y":0,"x":0,"width":1,"height":1},"opacity":1,"edgeAntialiasingMask":251658240,"height":38,"hidden":false,"anchorPoint":{"pointX":0.5,"pointY":0.5}},"layers":[{"animations":[],"layers":[],"texturedRectangle":{"singleTextureOpacity":1,"textXHeight":0.50728947368421051,"textBaseline":0.73504600958107413,"isBackgroundTexture":true,"isVerticalText":false,"textColor":[0.93333333730697632,0,0,1],"textureType":6},"initialState":{"affineTransform":[1,0,0,1,0,0],"masksToBounds":false,"rotation":0,"scale":1,"position":{"pointX":222.70001878513108,"pointY":38.381653677712052},"width":427,"sublayerTransform":[1,0,0,0,0,1,0,0,0,0,1,0,0,0,0,1],"contentsRect":{"y":0,"x":0,"width":1,"height":1},"opacity":1,"edgeAntialiasingMask":0,"height":38,"hidden":false,"anchorPoint":{"pointX":0.5,"pointY":0.5}},"texture":"F53BF4CCEC422DA7C11AC9737828F37B"}]}]},{"animations":[],"initialState":{"affineTransform":[1,0,0,1,0,0],"masksToBounds":false,"rotation":0,"scale":1,"position":{"pointX":480,"pointY":270},"width":960,"sublayerTransform":[1,0,0,0,0,1,0,0,0,0,1,0,0,0,0,1],"contentsRect":{"y":0,"x":0,"width":1,"height":1},"opacity":1,"edgeAntialiasingMask":251658240,"height":540,"hidden":false,"anchorPoint":{"pointX":0.5,"pointY":0.5}},"layers":[{"animations":[],"initialState":{"affineTransform":[1,0,0,1,0,0],"masksToBounds":false,"rotation":0,"scale":1,"position":{"pointX":250.30062866210938,"pointY":287.33566284179688},"width":319,"sublayerTransform":[1,0,0,0,0,1,0,0,0,0,1,0,0,0,0,1],"contentsRect":{"y":0,"x":0,"width":1,"height":1},"opacity":1,"edgeAntialiasingMask":251658240,"height":170,"hidden":false,"anchorPoint":{"pointX":0.5,"pointY":0.5}},"objectID":"CF4541FC-BC8D-4CC2-BA92-0DF01097CDC6","layers":[{"animations":[],"layers":[],"texturedRectangle":{"isBackgroundTexture":true,"singleTextureOpacity":1,"textureType":5,"textBaseline":0,"textXHeight":0,"isVerticalText":false},"initialState":{"affineTransform":[1,0,0,1,0,0],"masksToBounds":false,"rotation":0,"scale":1,"position":{"pointX":156.69937133789062,"pointY":82.664337158203125},"width":319,"sublayerTransform":[1,0,0,0,0,1,0,0,0,0,1,0,0,0,0,1],"contentsRect":{"y":0,"x":0,"width":1,"height":1},"opacity":1,"edgeAntialiasingMask":0,"height":170,"hidden":true,"anchorPoint":{"pointX":0.5,"pointY":0.5}},"texture":"AD08A39BDFC84D2E30FAF14B27AD06B8"}]}]},{"animations":[],"initialState":{"affineTransform":[1,0,0,1,0,0],"masksToBounds":false,"rotation":0,"scale":1,"position":{"pointX":480,"pointY":270},"width":960,"sublayerTransform":[1,0,0,0,0,1,0,0,0,0,1,0,0,0,0,1],"contentsRect":{"y":0,"x":0,"width":1,"height":1},"opacity":1,"edgeAntialiasingMask":251658240,"height":540,"hidden":false,"anchorPoint":{"pointX":0.5,"pointY":0.5}},"layers":[{"animations":[],"initialState":{"affineTransform":[1,0,0,1,0,0],"masksToBounds":false,"rotation":0,"scale":1,"position":{"pointX":221.35975868023525,"pointY":445.76275508383333},"width":412,"sublayerTransform":[1,0,0,0,0,1,0,0,0,0,1,0,0,0,0,1],"contentsRect":{"y":0,"x":0,"width":1,"height":1},"opacity":1,"edgeAntialiasingMask":251658240,"height":119,"hidden":false,"anchorPoint":{"pointX":0.5,"pointY":0.5}},"objectID":"3EB5EB02-7863-4ED3-AF07-7C45A22F1867","layers":[{"animations":[],"layers":[],"texturedRectangle":{"isBackgroundTexture":true,"singleTextureOpacity":1,"textureType":5,"textBaseline":0,"textXHeight":0,"isVerticalText":false},"initialState":{"affineTransform":[1,0,0,1,0,0],"masksToBounds":false,"rotation":0,"scale":1,"position":{"pointX":204.64024131976475,"pointY":58.237244916166674},"width":412,"sublayerTransform":[1,0,0,0,0,1,0,0,0,0,1,0,0,0,0,1],"contentsRect":{"y":0,"x":0,"width":1,"height":1},"opacity":1,"edgeAntialiasingMask":0,"height":119,"hidden":true,"anchorPoint":{"pointX":0.5,"pointY":0.5}},"texture":"A37863128BCF3FDA3869001B69046A9A"}]}]},{"animations":[],"initialState":{"affineTransform":[1,0,0,1,0,0],"masksToBounds":false,"rotation":0,"scale":1,"position":{"pointX":480,"pointY":270},"width":960,"sublayerTransform":[1,0,0,0,0,1,0,0,0,0,1,0,0,0,0,1],"contentsRect":{"y":0,"x":0,"width":1,"height":1},"opacity":1,"edgeAntialiasingMask":251658240,"height":540,"hidden":false,"anchorPoint":{"pointX":0.5,"pointY":0.5}},"layers":[{"animations":[],"initialState":{"affineTransform":[1,0,0,1,0,0],"masksToBounds":false,"rotation":0,"scale":1,"position":{"pointX":673.12914445644287,"pointY":303.46291363333154},"width":352,"sublayerTransform":[1,0,0,0,0,1,0,0,0,0,1,0,0,0,0,1],"contentsRect":{"y":0,"x":0,"width":1,"height":1},"opacity":1,"edgeAntialiasingMask":251658240,"height":387,"hidden":false,"anchorPoint":{"pointX":0.5,"pointY":0.5}},"objectID":"50D82587-25D7-4023-9DDE-7F2FFF91A79A","layers":[{"animations":[],"layers":[],"texturedRectangle":{"singleTextureOpacity":1,"textXHeight":0.022007751937984498,"textBaseline":0.9854685485156236,"isBackgroundTexture":true,"isVerticalText":false,"textColor":[0.08235294371843338,0.08235294371843338,0.08235294371843338,1],"textureType":6},"initialState":{"affineTransform":[1,0,0,1,0,0],"masksToBounds":false,"rotation":0,"scale":1,"position":{"pointX":177.87085554355713,"pointY":196.53708636666846},"width":352,"sublayerTransform":[1,0,0,0,0,1,0,0,0,0,1,0,0,0,0,1],"contentsRect":{"y":0,"x":0,"width":1,"height":1},"opacity":1,"edgeAntialiasingMask":0,"height":387,"hidden":true,"anchorPoint":{"pointX":0.5,"pointY":0.5}},"texture":"BE0EF8AC4767274F13F1A56A0F350673"}]}]},{"animations":[],"initialState":{"affineTransform":[1,0,0,1,0,0],"masksToBounds":false,"rotation":0,"scale":1,"position":{"pointX":480,"pointY":270},"width":960,"sublayerTransform":[1,0,0,0,0,1,0,0,0,0,1,0,0,0,0,1],"contentsRect":{"y":0,"x":0,"width":1,"height":1},"opacity":1,"edgeAntialiasingMask":251658240,"height":540,"hidden":false,"anchorPoint":{"pointX":0.5,"pointY":0.5}},"layers":[{"animations":[],"initialState":{"affineTransform":[1,0,0,1,0,0],"masksToBounds":false,"rotation":0,"scale":1,"position":{"pointX":249.8005468539117,"pointY":151.78023443447321},"width":318,"sublayerTransform":[1,0,0,0,0,1,0,0,0,0,1,0,0,0,0,1],"contentsRect":{"y":0,"x":0,"width":1,"height":1},"opacity":1,"edgeAntialiasingMask":251658240,"height":60,"hidden":false,"anchorPoint":{"pointX":0.5,"pointY":0.5}},"objectID":"13480192-313A-4D7E-A537-9EBFD811BCE6","layers":[{"animations":[],"layers":[],"texturedRectangle":{"isBackgroundTexture":true,"singleTextureOpacity":1,"textureType":5,"textBaseline":0,"textXHeight":0,"isVerticalText":false},"initialState":{"affineTransform":[1,0,0,1,0,0],"masksToBounds":false,"rotation":0,"scale":1,"position":{"pointX":157.1994531460883,"pointY":28.219765565526785},"width":318,"sublayerTransform":[1,0,0,0,0,1,0,0,0,0,1,0,0,0,0,1],"contentsRect":{"y":0,"x":0,"width":1,"height":1},"opacity":1,"edgeAntialiasingMask":0,"height":60,"hidden":true,"anchorPoint":{"pointX":0.5,"pointY":0.5}},"texture":"ED77A4173F60787A84F36B76E1B1DDF4"}]}]},{"animations":[],"initialState":{"affineTransform":[1,0,0,1,0,0],"masksToBounds":false,"rotation":0,"scale":1,"position":{"pointX":480,"pointY":270},"width":960,"sublayerTransform":[1,0,0,0,0,1,0,0,0,0,1,0,0,0,0,1],"contentsRect":{"y":0,"x":0,"width":1,"height":1},"opacity":1,"edgeAntialiasingMask":251658240,"height":540,"hidden":false,"anchorPoint":{"pointX":0.5,"pointY":0.5}},"layers":[{"animations":[],"initialState":{"affineTransform":[1,0,0,1,0,0],"masksToBounds":false,"rotation":0,"scale":1,"position":{"pointX":577.52881056001388,"pointY":53.22566870121409},"width":156,"sublayerTransform":[1,0,0,0,0,1,0,0,0,0,1,0,0,0,0,1],"contentsRect":{"y":0,"x":0,"width":1,"height":1},"opacity":1,"edgeAntialiasingMask":251658240,"height":98,"hidden":false,"anchorPoint":{"pointX":0.5,"pointY":0.5}},"layers":[{"animations":[],"layers":[],"texturedRectangle":{"isBackgroundTexture":true,"singleTextureOpacity":1,"textureType":5,"textBaseline":0,"textXHeight":0,"isVerticalText":false},"initialState":{"affineTransform":[1,0,0,1,0,0],"masksToBounds":false,"rotation":0,"scale":1,"position":{"pointX":76.471189439986119,"pointY":47.77433129878591},"width":156,"sublayerTransform":[1,0,0,0,0,1,0,0,0,0,1,0,0,0,0,1],"contentsRect":{"y":0,"x":0,"width":1,"height":1},"opacity":1,"edgeAntialiasingMask":0,"height":98,"hidden":false,"anchorPoint":{"pointX":0.5,"pointY":0.5}},"texture":"0C9392F1606516E5FD8AADE86409C03B"}]}]}]}},{"effects":[{"beginTime":0,"baseLayer":{"animations":[],"initialState":{"affineTransform":[1,0,0,1,0,0],"masksToBounds":false,"rotation":0,"scale":1,"position":{"pointX":250.30062866210938,"pointY":287.33566284179688},"width":319,"sublayerTransform":[1,0,0,0,0,1,0,0,0,0,1,0,0,0,0,1],"contentsRect":{"y":0,"x":0,"width":1,"height":1},"opacity":1,"edgeAntialiasingMask":251658240,"height":170,"hidden":false,"anchorPoint":{"pointX":0.5,"pointY":0.5}},"objectID":"CF4541FC-BC8D-4CC2-BA92-0DF01097CDC6","layers":[{"animations":[],"initialState":{"affineTransform":[1,0,0,1,0,0],"masksToBounds":false,"rotation":0,"scale":1,"position":{"pointX":389.19937133789062,"pointY":67.664337158203125},"width":319,"sublayerTransform":[1,0,0,0,0,1,0,0,0,0,1,-0.00070015824933551967,0,0,0,1],"contentsRect":{"y":0,"x":0,"width":1,"height":1},"opacity":1,"edgeAntialiasingMask":251658240,"height":170,"hidden":false,"anchorPoint":{"pointX":1.2200607251971494,"pointY":0.3980255126953125}},"layers":[{"animations":[{"additive":false,"timeOffset":0,"beginTime":1e-100,"repeatCount":0,"fillMode":"both","duration":0.001,"autoreverses":false,"animations":[{"additive":false,"timeOffset":0,"beginTime":0,"from":{"scalar":true},"repeatCount":0,"fillMode":"both","duration":0.0001,"autoreverses":false,"property":"hidden","to":{"scalar":false},"removedOnCompletion":true},{"additive":false,"timeOffset":0,"beginTime":0.0001,"from":{"scalar":false},"repeatCount":0,"fillMode":"forwards","duration":0.00089999999999999998,"autoreverses":false,"property":"hidden","to":{"scalar":false},"removedOnCompletion":true}],"removedOnCompletion":false}],"layers":[],"texturedRectangle":{"isBackgroundTexture":true,"singleTextureOpacity":1,"textureType":5,"textBaseline":0,"textXHeight":0,"isVerticalText":false},"initialState":{"affineTransform":[1,0,0,1,0,0],"masksToBounds":false,"rotation":0,"scale":1,"position":{"pointX":156.69937133789062,"pointY":82.664337158203125},"width":319,"sublayerTransform":[1,0,0,0,0,1,0,0,0,0,1,0,0,0,0,1],"contentsRect":{"y":0,"x":0,"width":1,"height":1},"opacity":1,"edgeAntialiasingMask":0,"height":170,"hidden":true,"anchorPoint":{"pointX":0.5,"pointY":0.5}},"texture":"AD08A39BDFC84D2E30FAF14B27AD06B8"}]}]},"effects":[],"duration":0.001,"type":"buildIn","attributes":{"direction":0},"name":"apple:appear","objectID":"CF4541FC-BC8D-4CC2-BA92-0DF01097CDC6"}],"automaticPlay":false,"hyperlinks":[],"accessibility":[{"text":"Veeam","targetRectangle":{"y":138.07188846681692,"x":306.32321233957276,"width":59.291999999999973,"height":23}},{"text":"OpenShift\\u2028Virtualization","targetRectangle":{"y":433.87047197613163,"x":87.555826198495311,"width":152.66399999999999,"height":62}},{"text":"Google Shape;4196;p228","targetRectangle":{"y":391.9639363079732,"x":279.04858162131859,"width":145.11181640625,"height":46.586929321289062}},{"text":"Google Shape;1631;p110","targetRectangle":{"y":497.10629293573453,"x":843.40777587890625,"width":76.84375,"height":17.968749999999943}},{"text":"Hundreds of Applications","targetRectangle":{"y":229.01204255930816,"x":188.29054962154714,"width":122.10000000000002,"height":52}},{"text":"6,200 Cores","targetRectangle":{"y":307.01204255930816,"x":189.42054962154717,"width":116.22,"height":26}},{"text":"Google Shape;4194;p228","targetRectangle":{"y":386.26275508383333,"x":15.359758680235245,"width":200.32347106933594,"height":53.941417694091797}},{"text":"Google Shape;4199;p228","targetRectangle":{"y":139.67527516136397,"x":96.273144134796894,"width":121.85031890869141,"height":19.688583374023438}},{"text":"Google Shape;4203;p228","targetRectangle":{"y":4.2256687012140901,"x":499.52881056001388,"width":152.59375,"height":95.250077659522503}},{"text":"Customer Success Story ","targetRectangle":{"y":15.216771233786972,"x":38.398406126367945,"width":429.82900000000001,"height":73.5}}],"baseLayer":{"animations":[],"initialState":{"affineTransform":[1,0,0,1,0,0],"masksToBounds":false,"rotation":0,"scale":1,"position":{"pointX":480,"pointY":270},"width":960,"sublayerTransform":[1,0,0,0,0,1,0,0,0,0,1,0,0,0,0,1],"contentsRect":{"y":0,"x":0,"width":1,"height":1},"opacity":1,"edgeAntialiasingMask":251658240,"height":540,"hidden":false,"anchorPoint":{"pointX":0.5,"pointY":0.5}},"layers":[{"animations":[],"initialState":{"affineTransform":[1,0,0,1,0,0],"masksToBounds":false,"rotation":0,"scale":1,"position":{"pointX":480,"pointY":270},"width":960,"sublayerTransform":[1,0,0,0,0,1,0,0,0,0,1,0,0,0,0,1],"contentsRect":{"y":0,"x":0,"width":1,"height":1},"opacity":1,"edgeAntialiasingMask":251658240,"height":540,"hidden":false,"anchorPoint":{"pointX":0.5,"pointY":0.5}},"layers":[{"animations":[],"initialState":{"affineTransform":[1,0,0,1,0,0],"masksToBounds":false,"rotation":0,"scale":1,"position":{"pointX":480,"pointY":270},"width":960,"sublayerTransform":[1,0,0,0,0,1,0,0,0,0,1,0,0,0,0,1],"contentsRect":{"y":0,"x":0,"width":1,"height":1},"opacity":1,"edgeAntialiasingMask":251658240,"height":540,"hidden":false,"anchorPoint":{"pointX":0.5,"pointY":0.5}},"layers":[{"animations":[],"layers":[],"texturedRectangle":{"isBackgroundTexture":true,"singleTextureOpacity":1,"textureType":1,"textBaseline":0,"textXHeight":0,"isVerticalText":false},"initialState":{"affineTransform":[1,0,0,1,0,0],"masksToBounds":false,"rotation":0,"scale":1,"position":{"pointX":480,"pointY":270},"width":960,"sublayerTransform":[1,0,0,0,0,1,0,0,0,0,1,0,0,0,0,1],"contentsRect":{"y":0,"x":0,"width":1,"height":1},"opacity":1,"edgeAntialiasingMask":0,"height":540,"hidden":false,"anchorPoint":{"pointX":0.5,"pointY":0.5}},"texture":"063F32FE31288BDCCDA81E55EF79D28B"}]}]},{"animations":[],"initialState":{"affineTransform":[1,0,0,1,0,0],"masksToBounds":false,"rotation":0,"scale":1,"position":{"pointX":480,"pointY":270},"width":960,"sublayerTransform":[1,0,0,0,0,1,0,0,0,0,1,0,0,0,0,1],"contentsRect":{"y":0,"x":0,"width":1,"height":1},"opacity":1,"edgeAntialiasingMask":251658240,"height":540,"hidden":false,"anchorPoint":{"pointX":0.5,"pointY":0.5}},"layers":[{"animations":[],"initialState":{"affineTransform":[1,0,0,1,0,0],"masksToBounds":false,"rotation":0,"scale":1,"position":{"pointX":36.982873535156244,"pointY":36.007948083001907},"width":4,"sublayerTransform":[1,0,0,0,0,1,0,0,0,0,1,0,0,0,0,1],"contentsRect":{"y":0,"x":0,"width":1,"height":1},"opacity":1,"edgeAntialiasingMask":251658240,"height":72,"hidden":false,"anchorPoint":{"pointX":0.5,"pointY":0.5}},"layers":[{"animations":[],"layers":[],"texturedRectangle":{"singleTextureOpacity":1,"textXHeight":0,"shapePath":{"lineWidth":1,"flatness":0.59999999999999998,"lineCapStyle":0,"elements":[{"type":"MoveToPoint","points":[[2.3578735351562443,70.811019979132766]]},{"type":"AddLine","points":[[2.3578735351562514,1.0079480830019065]]}],"windingRule":0,"lineJoinStyle":0,"miterLimit":10},"isBackgroundTexture":true,"textBaseline":0,"isVerticalText":false,"textureType":5},"initialState":{"affineTransform":[1,0,0,1,0,0],"masksToBounds":false,"rotation":0,"scale":1,"position":{"pointX":0.017126464843755684,"pointY":34.992051916998093},"width":4,"sublayerTransform":[1,0,0,0,0,1,0,0,0,0,1,0,0,0,0,1],"contentsRect":{"y":0,"x":0,"width":1,"height":1},"opacity":1,"edgeAntialiasingMask":0,"height":72,"hidden":false,"anchorPoint":{"pointX":0.5,"pointY":0.5}},"texture":"C54F8979F117F59627802EC083318BDC"}]}]},{"animations":[],"initialState":{"affineTransform":[1,0,0,1,0,0],"masksToBounds":false,"rotation":0,"scale":1,"position":{"pointX":480,"pointY":270},"width":960,"sublayerTransform":[1,0,0,0,0,1,0,0,0,0,1,0,0,0,0,1],"contentsRect":{"y":0,"x":0,"width":1,"height":1},"opacity":1,"edgeAntialiasingMask":251658240,"height":540,"hidden":false,"anchorPoint":{"pointX":0.5,"pointY":0.5}},"layers":[{"animations":[],"initialState":{"affineTransform":[1,0,0,1,0,0],"masksToBounds":false,"rotation":0,"scale":1,"position":{"pointX":36.982244110107416,"pointY":523.04723928371163},"width":4,"sublayerTransform":[1,0,0,0,0,1,0,0,0,0,1,0,0,0,0,1],"contentsRect":{"y":0,"x":0,"width":1,"height":1},"opacity":1,"edgeAntialiasingMask":251658240,"height":38,"hidden":false,"anchorPoint":{"pointX":0.5,"pointY":0.5}},"layers":[{"animations":[],"layers":[],"texturedRectangle":{"singleTextureOpacity":1,"textXHeight":0,"shapePath":{"lineWidth":1,"flatness":0.59999999999999998,"lineCapStyle":0,"elements":[{"type":"MoveToPoint","points":[[2.3572441101074162,36.999995719729441]]},{"type":"AddLine","points":[[2.3572441101074162,1.0472392837116331]]}],"windingRule":0,"lineJoinStyle":0,"miterLimit":10},"isBackgroundTexture":true,"textBaseline":0,"isVerticalText":false,"textureType":5},"initialState":{"affineTransform":[1,0,0,1,0,0],"masksToBounds":false,"rotation":0,"scale":1,"position":{"pointX":0.017755889892583809,"pointY":17.952760716288367},"width":4,"sublayerTransform":[1,0,0,0,0,1,0,0,0,0,1,0,0,0,0,1],"contentsRect":{"y":0,"x":0,"width":1,"height":1},"opacity":1,"edgeAntialiasingMask":0,"height":38,"hidden":false,"anchorPoint":{"pointX":0.5,"pointY":0.5}},"texture":"4FC9773900971738E5F56D1D94665F05"}]}]},{"animations":[],"initialState":{"affineTransform":[1,0,0,1,0,0],"masksToBounds":false,"rotation":0,"scale":1,"position":{"pointX":480,"pointY":270},"width":960,"sublayerTransform":[1,0,0,0,0,1,0,0,0,0,1,0,0,0,0,1],"contentsRect":{"y":0,"x":0,"width":1,"height":1},"opacity":1,"edgeAntialiasingMask":251658240,"height":540,"hidden":false,"anchorPoint":{"pointX":0.5,"pointY":0.5}},"layers":[{"animations":[],"initialState":{"affineTransform":[1,0,0,1,0,0],"masksToBounds":false,"rotation":0,"scale":1,"position":{"pointX":883.40777587890625,"pointY":507.60629293573453},"width":80,"sublayerTransform":[1,0,0,0,0,1,0,0,0,0,1,0,0,0,0,1],"contentsRect":{"y":0,"x":0,"width":1,"height":1},"opacity":1,"edgeAntialiasingMask":251658240,"height":21,"hidden":false,"anchorPoint":{"pointX":0.5,"pointY":0.5}},"layers":[{"animations":[],"layers":[],"texturedRectangle":{"isBackgroundTexture":true,"singleTextureOpacity":1,"textureType":5,"textBaseline":0,"textXHeight":0,"isVerticalText":false},"initialState":{"affineTransform":[1,0,0,1,0,0],"masksToBounds":false,"rotation":0,"scale":1,"position":{"pointX":38.59222412109375,"pointY":9.3937070642654703},"width":80,"sublayerTransform":[1,0,0,0,0,1,0,0,0,0,1,0,0,0,0,1],"contentsRect":{"y":0,"x":0,"width":1,"height":1},"opacity":1,"edgeAntialiasingMask":0,"height":21,"hidden":false,"anchorPoint":{"pointX":0.5,"pointY":0.5}},"texture":"9BD4D1AA1ECF6CB5EDB3E73F5C0E10B4"}]}]},{"animations":[],"initialState":{"affineTransform":[1,0,0,1,0,0],"masksToBounds":false,"rotation":0,"scale":1,"position":{"pointX":480,"pointY":270},"width":960,"sublayerTransform":[1,0,0,0,0,1,0,0,0,0,1,0,0,0,0,1],"contentsRect":{"y":0,"x":0,"width":1,"height":1},"opacity":1,"edgeAntialiasingMask":251658240,"height":540,"hidden":false,"anchorPoint":{"pointX":0.5,"pointY":0.5}},"layers":[{"animations":[],"initialState":{"affineTransform":[1,0,0,1,0,0],"masksToBounds":false,"rotation":0,"scale":1,"position":{"pointX":242.29998121486892,"pointY":24.618346322287948},"width":427,"sublayerTransform":[1,0,0,0,0,1,0,0,0,0,1,0,0,0,0,1],"contentsRect":{"y":0,"x":0,"width":1,"height":1},"opacity":1,"edgeAntialiasingMask":251658240,"height":38,"hidden":false,"anchorPoint":{"pointX":0.5,"pointY":0.5}},"layers":[{"animations":[],"layers":[],"texturedRectangle":{"singleTextureOpacity":1,"textXHeight":0.50728947368421051,"textBaseline":0.73504600958107413,"isBackgroundTexture":true,"isVerticalText":false,"textColor":[0.93333333730697632,0,0,1],"textureType":6},"initialState":{"affineTransform":[1,0,0,1,0,0],"masksToBounds":false,"rotation":0,"scale":1,"position":{"pointX":222.70001878513108,"pointY":38.381653677712052},"width":427,"sublayerTransform":[1,0,0,0,0,1,0,0,0,0,1,0,0,0,0,1],"contentsRect":{"y":0,"x":0,"width":1,"height":1},"opacity":1,"edgeAntialiasingMask":0,"height":38,"hidden":false,"anchorPoint":{"pointX":0.5,"pointY":0.5}},"texture":"F53BF4CCEC422DA7C11AC9737828F37B"}]}]},{"animations":[],"initialState":{"affineTransform":[1,0,0,1,0,0],"masksToBounds":false,"rotation":0,"scale":1,"position":{"pointX":480,"pointY":270},"width":960,"sublayerTransform":[1,0,0,0,0,1,0,0,0,0,1,0,0,0,0,1],"contentsRect":{"y":0,"x":0,"width":1,"height":1},"opacity":1,"edgeAntialiasingMask":251658240,"height":540,"hidden":false,"anchorPoint":{"pointX":0.5,"pointY":0.5}},"layers":[{"animations":[],"initialState":{"affineTransform":[1,0,0,1,0,0],"masksToBounds":false,"rotation":0,"scale":1,"position":{"pointX":250.30062866210938,"pointY":287.33566284179688},"width":319,"sublayerTransform":[1,0,0,0,0,1,0,0,0,0,1,0,0,0,0,1],"contentsRect":{"y":0,"x":0,"width":1,"height":1},"opacity":1,"edgeAntialiasingMask":251658240,"height":170,"hidden":false,"anchorPoint":{"pointX":0.5,"pointY":0.5}},"objectID":"CF4541FC-BC8D-4CC2-BA92-0DF01097CDC6","layers":[{"animations":[],"layers":[],"texturedRectangle":{"isBackgroundTexture":true,"singleTextureOpacity":1,"textureType":5,"textBaseline":0,"textXHeight":0,"isVerticalText":false},"initialState":{"affineTransform":[1,0,0,1,0,0],"masksToBounds":false,"rotation":0,"scale":1,"position":{"pointX":156.69937133789062,"pointY":82.664337158203125},"width":319,"sublayerTransform":[1,0,0,0,0,1,0,0,0,0,1,0,0,0,0,1],"contentsRect":{"y":0,"x":0,"width":1,"height":1},"opacity":1,"edgeAntialiasingMask":0,"height":170,"hidden":true,"anchorPoint":{"pointX":0.5,"pointY":0.5}},"texture":"AD08A39BDFC84D2E30FAF14B27AD06B8"}]}]},{"animations":[],"initialState":{"affineTransform":[1,0,0,1,0,0],"masksToBounds":false,"rotation":0,"scale":1,"position":{"pointX":480,"pointY":270},"width":960,"sublayerTransform":[1,0,0,0,0,1,0,0,0,0,1,0,0,0,0,1],"contentsRect":{"y":0,"x":0,"width":1,"height":1},"opacity":1,"edgeAntialiasingMask":251658240,"height":540,"hidden":false,"anchorPoint":{"pointX":0.5,"pointY":0.5}},"layers":[{"animations":[],"initialState":{"affineTransform":[1,0,0,1,0,0],"masksToBounds":false,"rotation":0,"scale":1,"position":{"pointX":221.35975868023525,"pointY":445.76275508383333},"width":412,"sublayerTransform":[1,0,0,0,0,1,0,0,0,0,1,0,0,0,0,1],"contentsRect":{"y":0,"x":0,"width":1,"height":1},"opacity":1,"edgeAntialiasingMask":251658240,"height":119,"hidden":false,"anchorPoint":{"pointX":0.5,"pointY":0.5}},"objectID":"3EB5EB02-7863-4ED3-AF07-7C45A22F1867","layers":[{"animations":[],"layers":[],"texturedRectangle":{"isBackgroundTexture":true,"singleTextureOpacity":1,"textureType":5,"textBaseline":0,"textXHeight":0,"isVerticalText":false},"initialState":{"affineTransform":[1,0,0,1,0,0],"masksToBounds":false,"rotation":0,"scale":1,"position":{"pointX":204.64024131976475,"pointY":58.237244916166674},"width":412,"sublayerTransform":[1,0,0,0,0,1,0,0,0,0,1,0,0,0,0,1],"contentsRect":{"y":0,"x":0,"width":1,"height":1},"opacity":1,"edgeAntialiasingMask":0,"height":119,"hidden":true,"anchorPoint":{"pointX":0.5,"pointY":0.5}},"texture":"A37863128BCF3FDA3869001B69046A9A"}]}]},{"animations":[],"initialState":{"affineTransform":[1,0,0,1,0,0],"masksToBounds":false,"rotation":0,"scale":1,"position":{"pointX":480,"pointY":270},"width":960,"sublayerTransform":[1,0,0,0,0,1,0,0,0,0,1,0,0,0,0,1],"contentsRect":{"y":0,"x":0,"width":1,"height":1},"opacity":1,"edgeAntialiasingMask":251658240,"height":540,"hidden":false,"anchorPoint":{"pointX":0.5,"pointY":0.5}},"layers":[{"animations":[],"initialState":{"affineTransform":[1,0,0,1,0,0],"masksToBounds":false,"rotation":0,"scale":1,"position":{"pointX":673.12914445644287,"pointY":303.46291363333154},"width":352,"sublayerTransform":[1,0,0,0,0,1,0,0,0,0,1,0,0,0,0,1],"contentsRect":{"y":0,"x":0,"width":1,"height":1},"opacity":1,"edgeAntialiasingMask":251658240,"height":387,"hidden":false,"anchorPoint":{"pointX":0.5,"pointY":0.5}},"objectID":"50D82587-25D7-4023-9DDE-7F2FFF91A79A","layers":[{"animations":[],"layers":[],"texturedRectangle":{"singleTextureOpacity":1,"textXHeight":0.022007751937984498,"textBaseline":0.9854685485156236,"isBackgroundTexture":true,"isVerticalText":false,"textColor":[0.08235294371843338,0.08235294371843338,0.08235294371843338,1],"textureType":6},"initialState":{"affineTransform":[1,0,0,1,0,0],"masksToBounds":false,"rotation":0,"scale":1,"position":{"pointX":177.87085554355713,"pointY":196.53708636666846},"width":352,"sublayerTransform":[1,0,0,0,0,1,0,0,0,0,1,0,0,0,0,1],"contentsRect":{"y":0,"x":0,"width":1,"height":1},"opacity":1,"edgeAntialiasingMask":0,"height":387,"hidden":true,"anchorPoint":{"pointX":0.5,"pointY":0.5}},"texture":"BE0EF8AC4767274F13F1A56A0F350673"}]}]},{"animations":[],"initialState":{"affineTransform":[1,0,0,1,0,0],"masksToBounds":false,"rotation":0,"scale":1,"position":{"pointX":480,"pointY":270},"width":960,"sublayerTransform":[1,0,0,0,0,1,0,0,0,0,1,0,0,0,0,1],"contentsRect":{"y":0,"x":0,"width":1,"height":1},"opacity":1,"edgeAntialiasingMask":251658240,"height":540,"hidden":false,"anchorPoint":{"pointX":0.5,"pointY":0.5}},"layers":[{"animations":[],"initialState":{"affineTransform":[1,0,0,1,0,0],"masksToBounds":false,"rotation":0,"scale":1,"position":{"pointX":249.8005468539117,"pointY":151.78023443447321},"width":318,"sublayerTransform":[1,0,0,0,0,1,0,0,0,0,1,0,0,0,0,1],"contentsRect":{"y":0,"x":0,"width":1,"height":1},"opacity":1,"edgeAntialiasingMask":251658240,"height":60,"hidden":false,"anchorPoint":{"pointX":0.5,"pointY":0.5}},"objectID":"13480192-313A-4D7E-A537-9EBFD811BCE6","layers":[{"animations":[],"layers":[],"texturedRectangle":{"isBackgroundTexture":true,"singleTextureOpacity":1,"textureType":5,"textBaseline":0,"textXHeight":0,"isVerticalText":false},"initialState":{"affineTransform":[1,0,0,1,0,0],"masksToBounds":false,"rotation":0,"scale":1,"position":{"pointX":157.1994531460883,"pointY":28.219765565526785},"width":318,"sublayerTransform":[1,0,0,0,0,1,0,0,0,0,1,0,0,0,0,1],"contentsRect":{"y":0,"x":0,"width":1,"height":1},"opacity":1,"edgeAntialiasingMask":0,"height":60,"hidden":false,"anchorPoint":{"pointX":0.5,"pointY":0.5}},"texture":"ED77A4173F60787A84F36B76E1B1DDF4"}]}]},{"animations":[],"initialState":{"affineTransform":[1,0,0,1,0,0],"masksToBounds":false,"rotation":0,"scale":1,"position":{"pointX":480,"pointY":270},"width":960,"sublayerTransform":[1,0,0,0,0,1,0,0,0,0,1,0,0,0,0,1],"contentsRect":{"y":0,"x":0,"width":1,"height":1},"opacity":1,"edgeAntialiasingMask":251658240,"height":540,"hidden":false,"anchorPoint":{"pointX":0.5,"pointY":0.5}},"layers":[{"animations":[],"initialState":{"affineTransform":[1,0,0,1,0,0],"masksToBounds":false,"rotation":0,"scale":1,"position":{"pointX":577.52881056001388,"pointY":53.22566870121409},"width":156,"sublayerTransform":[1,0,0,0,0,1,0,0,0,0,1,0,0,0,0,1],"contentsRect":{"y":0,"x":0,"width":1,"height":1},"opacity":1,"edgeAntialiasingMask":251658240,"height":98,"hidden":false,"anchorPoint":{"pointX":0.5,"pointY":0.5}},"layers":[{"animations":[],"layers":[],"texturedRectangle":{"isBackgroundTexture":true,"singleTextureOpacity":1,"textureType":5,"textBaseline":0,"textXHeight":0,"isVerticalText":false},"initialState":{"affineTransform":[1,0,0,1,0,0],"masksToBounds":false,"rotation":0,"scale":1,"position":{"pointX":76.471189439986119,"pointY":47.77433129878591},"width":156,"sublayerTransform":[1,0,0,0,0,1,0,0,0,0,1,0,0,0,0,1],"contentsRect":{"y":0,"x":0,"width":1,"height":1},"opacity":1,"edgeAntialiasingMask":0,"height":98,"hidden":false,"anchorPoint":{"pointX":0.5,"pointY":0.5}},"texture":"0C9392F1606516E5FD8AADE86409C03B"}]}]}]}},{"effects":[{"beginTime":0,"baseLayer":{"animations":[],"initialState":{"affineTransform":[1,0,0,1,0,0],"masksToBounds":false,"rotation":0,"scale":1,"position":{"pointX":221.35975868023525,"pointY":445.76275508383333},"width":412,"sublayerTransform":[1,0,0,0,0,1,0,0,0,0,1,0,0,0,0,1],"contentsRect":{"y":0,"x":0,"width":1,"height":1},"opacity":1,"edgeAntialiasingMask":251658240,"height":119,"hidden":false,"anchorPoint":{"pointX":0.5,"pointY":0.5}},"objectID":"3EB5EB02-7863-4ED3-AF07-7C45A22F1867","layers":[{"animations":[],"initialState":{"affineTransform":[1,0,0,1,0,0],"masksToBounds":false,"rotation":0,"scale":1,"position":{"pointX":464.64024131976475,"pointY":-116.26275508383333},"width":412,"sublayerTransform":[1,0,0,0,0,1,0,0,0,0,1,-0.00070015824933551967,0,0,0,1],"contentsRect":{"y":0,"x":0,"width":1,"height":1},"opacity":1,"edgeAntialiasingMask":251658240,"height":119,"hidden":false,"anchorPoint":{"pointX":1.1277675760188466,"pointY":-0.97699794188095235}},"layers":[{"animations":[{"additive":false,"timeOffset":0,"beginTime":1e-100,"repeatCount":0,"fillMode":"both","duration":0.001,"autoreverses":false,"animations":[{"additive":false,"timeOffset":0,"beginTime":0,"from":{"scalar":true},"repeatCount":0,"fillMode":"both","duration":0.0001,"autoreverses":false,"property":"hidden","to":{"scalar":false},"removedOnCompletion":true},{"additive":false,"timeOffset":0,"beginTime":0.0001,"from":{"scalar":false},"repeatCount":0,"fillMode":"forwards","duration":0.00089999999999999998,"autoreverses":false,"property":"hidden","to":{"scalar":false},"removedOnCompletion":true}],"removedOnCompletion":false}],"layers":[],"texturedRectangle":{"isBackgroundTexture":true,"singleTextureOpacity":1,"textureType":5,"textBaseline":0,"textXHeight":0,"isVerticalText":false},"initialState":{"affineTransform":[1,0,0,1,0,0],"masksToBounds":false,"rotation":0,"scale":1,"position":{"pointX":204.64024131976475,"pointY":58.237244916166674},"width":412,"sublayerTransform":[1,0,0,0,0,1,0,0,0,0,1,0,0,0,0,1],"contentsRect":{"y":0,"x":0,"width":1,"height":1},"opacity":1,"edgeAntialiasingMask":0,"height":119,"hidden":true,"anchorPoint":{"pointX":0.5,"pointY":0.5}},"texture":"A37863128BCF3FDA3869001B69046A9A"}]}]},"effects":[],"duration":0.001,"type":"buildIn","attributes":{"direction":0},"name":"apple:appear","objectID":"3EB5EB02-7863-4ED3-AF07-7C45A22F1867"}],"automaticPlay":false,"hyperlinks":[],"accessibility":[{"text":"Veeam","targetRectangle":{"y":138.07188846681692,"x":306.32321233957276,"width":59.291999999999973,"height":23}},{"text":"OpenShift\\u2028Virtualization","targetRectangle":{"y":433.87047197613163,"x":87.555826198495311,"width":152.66399999999999,"height":62}},{"text":"Google Shape;4196;p228","targetRectangle":{"y":391.9639363079732,"x":279.04858162131859,"width":145.11181640625,"height":46.586929321289062}},{"text":"Google Shape;1631;p110","targetRectangle":{"y":497.10629293573453,"x":843.40777587890625,"width":76.84375,"height":17.968749999999943}},{"text":"Hundreds of Applications","targetRectangle":{"y":229.01204255930816,"x":188.29054962154714,"width":122.10000000000002,"height":52}},{"text":"6,200 Cores","targetRectangle":{"y":307.01204255930816,"x":189.42054962154717,"width":116.22,"height":26}},{"text":"Google Shape;4194;p228","targetRectangle":{"y":386.26275508383333,"x":15.359758680235245,"width":200.32347106933594,"height":53.941417694091797}},{"text":"Google Shape;4199;p228","targetRectangle":{"y":139.67527516136397,"x":96.273144134796894,"width":121.85031890869141,"height":19.688583374023438}},{"text":"Google Shape;4203;p228","targetRectangle":{"y":4.2256687012140901,"x":499.52881056001388,"width":152.59375,"height":95.250077659522503}},{"text":"Customer Success Story ","targetRectangle":{"y":15.216771233786972,"x":38.398406126367945,"width":429.82900000000001,"height":73.5}}],"baseLayer":{"animations":[],"initialState":{"affineTransform":[1,0,0,1,0,0],"masksToBounds":false,"rotation":0,"scale":1,"position":{"pointX":480,"pointY":270},"width":960,"sublayerTransform":[1,0,0,0,0,1,0,0,0,0,1,0,0,0,0,1],"contentsRect":{"y":0,"x":0,"width":1,"height":1},"opacity":1,"edgeAntialiasingMask":251658240,"height":540,"hidden":false,"anchorPoint":{"pointX":0.5,"pointY":0.5}},"layers":[{"animations":[],"initialState":{"affineTransform":[1,0,0,1,0,0],"masksToBounds":false,"rotation":0,"scale":1,"position":{"pointX":480,"pointY":270},"width":960,"sublayerTransform":[1,0,0,0,0,1,0,0,0,0,1,0,0,0,0,1],"contentsRect":{"y":0,"x":0,"width":1,"height":1},"opacity":1,"edgeAntialiasingMask":251658240,"height":540,"hidden":false,"anchorPoint":{"pointX":0.5,"pointY":0.5}},"layers":[{"animations":[],"initialState":{"affineTransform":[1,0,0,1,0,0],"masksToBounds":false,"rotation":0,"scale":1,"position":{"pointX":480,"pointY":270},"width":960,"sublayerTransform":[1,0,0,0,0,1,0,0,0,0,1,0,0,0,0,1],"contentsRect":{"y":0,"x":0,"width":1,"height":1},"opacity":1,"edgeAntialiasingMask":251658240,"height":540,"hidden":false,"anchorPoint":{"pointX":0.5,"pointY":0.5}},"layers":[{"animations":[],"layers":[],"texturedRectangle":{"isBackgroundTexture":true,"singleTextureOpacity":1,"textureType":1,"textBaseline":0,"textXHeight":0,"isVerticalText":false},"initialState":{"affineTransform":[1,0,0,1,0,0],"masksToBounds":false,"rotation":0,"scale":1,"position":{"pointX":480,"pointY":270},"width":960,"sublayerTransform":[1,0,0,0,0,1,0,0,0,0,1,0,0,0,0,1],"contentsRect":{"y":0,"x":0,"width":1,"height":1},"opacity":1,"edgeAntialiasingMask":0,"height":540,"hidden":false,"anchorPoint":{"pointX":0.5,"pointY":0.5}},"texture":"063F32FE31288BDCCDA81E55EF79D28B"}]}]},{"animations":[],"initialState":{"affineTransform":[1,0,0,1,0,0],"masksToBounds":false,"rotation":0,"scale":1,"position":{"pointX":480,"pointY":270},"width":960,"sublayerTransform":[1,0,0,0,0,1,0,0,0,0,1,0,0,0,0,1],"contentsRect":{"y":0,"x":0,"width":1,"height":1},"opacity":1,"edgeAntialiasingMask":251658240,"height":540,"hidden":false,"anchorPoint":{"pointX":0.5,"pointY":0.5}},"layers":[{"animations":[],"initialState":{"affineTransform":[1,0,0,1,0,0],"masksToBounds":false,"rotation":0,"scale":1,"position":{"pointX":36.982873535156244,"pointY":36.007948083001907},"width":4,"sublayerTransform":[1,0,0,0,0,1,0,0,0,0,1,0,0,0,0,1],"contentsRect":{"y":0,"x":0,"width":1,"height":1},"opacity":1,"edgeAntialiasingMask":251658240,"height":72,"hidden":false,"anchorPoint":{"pointX":0.5,"pointY":0.5}},"layers":[{"animations":[],"layers":[],"texturedRectangle":{"singleTextureOpacity":1,"textXHeight":0,"shapePath":{"lineWidth":1,"flatness":0.59999999999999998,"lineCapStyle":0,"elements":[{"type":"MoveToPoint","points":[[2.3578735351562443,70.811019979132766]]},{"type":"AddLine","points":[[2.3578735351562514,1.0079480830019065]]}],"windingRule":0,"lineJoinStyle":0,"miterLimit":10},"isBackgroundTexture":true,"textBaseline":0,"isVerticalText":false,"textureType":5},"initialState":{"affineTransform":[1,0,0,1,0,0],"masksToBounds":false,"rotation":0,"scale":1,"position":{"pointX":0.017126464843755684,"pointY":34.992051916998093},"width":4,"sublayerTransform":[1,0,0,0,0,1,0,0,0,0,1,0,0,0,0,1],"contentsRect":{"y":0,"x":0,"width":1,"height":1},"opacity":1,"edgeAntialiasingMask":0,"height":72,"hidden":false,"anchorPoint":{"pointX":0.5,"pointY":0.5}},"texture":"C54F8979F117F59627802EC083318BDC"}]}]},{"animations":[],"initialState":{"affineTransform":[1,0,0,1,0,0],"masksToBounds":false,"rotation":0,"scale":1,"position":{"pointX":480,"pointY":270},"width":960,"sublayerTransform":[1,0,0,0,0,1,0,0,0,0,1,0,0,0,0,1],"contentsRect":{"y":0,"x":0,"width":1,"height":1},"opacity":1,"edgeAntialiasingMask":251658240,"height":540,"hidden":false,"anchorPoint":{"pointX":0.5,"pointY":0.5}},"layers":[{"animations":[],"initialState":{"affineTransform":[1,0,0,1,0,0],"masksToBounds":false,"rotation":0,"scale":1,"position":{"pointX":36.982244110107416,"pointY":523.04723928371163},"width":4,"sublayerTransform":[1,0,0,0,0,1,0,0,0,0,1,0,0,0,0,1],"contentsRect":{"y":0,"x":0,"width":1,"height":1},"opacity":1,"edgeAntialiasingMask":251658240,"height":38,"hidden":false,"anchorPoint":{"pointX":0.5,"pointY":0.5}},"layers":[{"animations":[],"layers":[],"texturedRectangle":{"singleTextureOpacity":1,"textXHeight":0,"shapePath":{"lineWidth":1,"flatness":0.59999999999999998,"lineCapStyle":0,"elements":[{"type":"MoveToPoint","points":[[2.3572441101074162,36.999995719729441]]},{"type":"AddLine","points":[[2.3572441101074162,1.0472392837116331]]}],"windingRule":0,"lineJoinStyle":0,"miterLimit":10},"isBackgroundTexture":true,"textBaseline":0,"isVerticalText":false,"textureType":5},"initialState":{"affineTransform":[1,0,0,1,0,0],"masksToBounds":false,"rotation":0,"scale":1,"position":{"pointX":0.017755889892583809,"pointY":17.952760716288367},"width":4,"sublayerTransform":[1,0,0,0,0,1,0,0,0,0,1,0,0,0,0,1],"contentsRect":{"y":0,"x":0,"width":1,"height":1},"opacity":1,"edgeAntialiasingMask":0,"height":38,"hidden":false,"anchorPoint":{"pointX":0.5,"pointY":0.5}},"texture":"4FC9773900971738E5F56D1D94665F05"}]}]},{"animations":[],"initialState":{"affineTransform":[1,0,0,1,0,0],"masksToBounds":false,"rotation":0,"scale":1,"position":{"pointX":480,"pointY":270},"width":960,"sublayerTransform":[1,0,0,0,0,1,0,0,0,0,1,0,0,0,0,1],"contentsRect":{"y":0,"x":0,"width":1,"height":1},"opacity":1,"edgeAntialiasingMask":251658240,"height":540,"hidden":false,"anchorPoint":{"pointX":0.5,"pointY":0.5}},"layers":[{"animations":[],"initialState":{"affineTransform":[1,0,0,1,0,0],"masksToBounds":false,"rotation":0,"scale":1,"position":{"pointX":883.40777587890625,"pointY":507.60629293573453},"width":80,"sublayerTransform":[1,0,0,0,0,1,0,0,0,0,1,0,0,0,0,1],"contentsRect":{"y":0,"x":0,"width":1,"height":1},"opacity":1,"edgeAntialiasingMask":251658240,"height":21,"hidden":false,"anchorPoint":{"pointX":0.5,"pointY":0.5}},"layers":[{"animations":[],"layers":[],"texturedRectangle":{"isBackgroundTexture":true,"singleTextureOpacity":1,"textureType":5,"textBaseline":0,"textXHeight":0,"isVerticalText":false},"initialState":{"affineTransform":[1,0,0,1,0,0],"masksToBounds":false,"rotation":0,"scale":1,"position":{"pointX":38.59222412109375,"pointY":9.3937070642654703},"width":80,"sublayerTransform":[1,0,0,0,0,1,0,0,0,0,1,0,0,0,0,1],"contentsRect":{"y":0,"x":0,"width":1,"height":1},"opacity":1,"edgeAntialiasingMask":0,"height":21,"hidden":false,"anchorPoint":{"pointX":0.5,"pointY":0.5}},"texture":"9BD4D1AA1ECF6CB5EDB3E73F5C0E10B4"}]}]},{"animations":[],"initialState":{"affineTransform":[1,0,0,1,0,0],"masksToBounds":false,"rotation":0,"scale":1,"position":{"pointX":480,"pointY":270},"width":960,"sublayerTransform":[1,0,0,0,0,1,0,0,0,0,1,0,0,0,0,1],"contentsRect":{"y":0,"x":0,"width":1,"height":1},"opacity":1,"edgeAntialiasingMask":251658240,"height":540,"hidden":false,"anchorPoint":{"pointX":0.5,"pointY":0.5}},"layers":[{"animations":[],"initialState":{"affineTransform":[1,0,0,1,0,0],"masksToBounds":false,"rotation":0,"scale":1,"position":{"pointX":242.29998121486892,"pointY":24.618346322287948},"width":427,"sublayerTransform":[1,0,0,0,0,1,0,0,0,0,1,0,0,0,0,1],"contentsRect":{"y":0,"x":0,"width":1,"height":1},"opacity":1,"edgeAntialiasingMask":251658240,"height":38,"hidden":false,"anchorPoint":{"pointX":0.5,"pointY":0.5}},"layers":[{"animations":[],"layers":[],"texturedRectangle":{"singleTextureOpacity":1,"textXHeight":0.50728947368421051,"textBaseline":0.73504600958107413,"isBackgroundTexture":true,"isVerticalText":false,"textColor":[0.93333333730697632,0,0,1],"textureType":6},"initialState":{"affineTransform":[1,0,0,1,0,0],"masksToBounds":false,"rotation":0,"scale":1,"position":{"pointX":222.70001878513108,"pointY":38.381653677712052},"width":427,"sublayerTransform":[1,0,0,0,0,1,0,0,0,0,1,0,0,0,0,1],"contentsRect":{"y":0,"x":0,"width":1,"height":1},"opacity":1,"edgeAntialiasingMask":0,"height":38,"hidden":false,"anchorPoint":{"pointX":0.5,"pointY":0.5}},"texture":"F53BF4CCEC422DA7C11AC9737828F37B"}]}]},{"animations":[],"initialState":{"affineTransform":[1,0,0,1,0,0],"masksToBounds":false,"rotation":0,"scale":1,"position":{"pointX":480,"pointY":270},"width":960,"sublayerTransform":[1,0,0,0,0,1,0,0,0,0,1,0,0,0,0,1],"contentsRect":{"y":0,"x":0,"width":1,"height":1},"opacity":1,"edgeAntialiasingMask":251658240,"height":540,"hidden":false,"anchorPoint":{"pointX":0.5,"pointY":0.5}},"layers":[{"animations":[],"initialState":{"affineTransform":[1,0,0,1,0,0],"masksToBounds":false,"rotation":0,"scale":1,"position":{"pointX":250.30062866210938,"pointY":287.33566284179688},"width":319,"sublayerTransform":[1,0,0,0,0,1,0,0,0,0,1,0,0,0,0,1],"contentsRect":{"y":0,"x":0,"width":1,"height":1},"opacity":1,"edgeAntialiasingMask":251658240,"height":170,"hidden":false,"anchorPoint":{"pointX":0.5,"pointY":0.5}},"objectID":"CF4541FC-BC8D-4CC2-BA92-0DF01097CDC6","layers":[{"animations":[],"layers":[],"texturedRectangle":{"isBackgroundTexture":true,"singleTextureOpacity":1,"textureType":5,"textBaseline":0,"textXHeight":0,"isVerticalText":false},"initialState":{"affineTransform":[1,0,0,1,0,0],"masksToBounds":false,"rotation":0,"scale":1,"position":{"pointX":156.69937133789062,"pointY":82.664337158203125},"width":319,"sublayerTransform":[1,0,0,0,0,1,0,0,0,0,1,0,0,0,0,1],"contentsRect":{"y":0,"x":0,"width":1,"height":1},"opacity":1,"edgeAntialiasingMask":0,"height":170,"hidden":false,"anchorPoint":{"pointX":0.5,"pointY":0.5}},"texture":"AD08A39BDFC84D2E30FAF14B27AD06B8"}]}]},{"animations":[],"initialState":{"affineTransform":[1,0,0,1,0,0],"masksToBounds":false,"rotation":0,"scale":1,"position":{"pointX":480,"pointY":270},"width":960,"sublayerTransform":[1,0,0,0,0,1,0,0,0,0,1,0,0,0,0,1],"contentsRect":{"y":0,"x":0,"width":1,"height":1},"opacity":1,"edgeAntialiasingMask":251658240,"height":540,"hidden":false,"anchorPoint":{"pointX":0.5,"pointY":0.5}},"layers":[{"animations":[],"initialState":{"affineTransform":[1,0,0,1,0,0],"masksToBounds":false,"rotation":0,"scale":1,"position":{"pointX":221.35975868023525,"pointY":445.76275508383333},"width":412,"sublayerTransform":[1,0,0,0,0,1,0,0,0,0,1,0,0,0,0,1],"contentsRect":{"y":0,"x":0,"width":1,"height":1},"opacity":1,"edgeAntialiasingMask":251658240,"height":119,"hidden":false,"anchorPoint":{"pointX":0.5,"pointY":0.5}},"objectID":"3EB5EB02-7863-4ED3-AF07-7C45A22F1867","layers":[{"animations":[],"layers":[],"texturedRectangle":{"isBackgroundTexture":true,"singleTextureOpacity":1,"textureType":5,"textBaseline":0,"textXHeight":0,"isVerticalText":false},"initialState":{"affineTransform":[1,0,0,1,0,0],"masksToBounds":false,"rotation":0,"scale":1,"position":{"pointX":204.64024131976475,"pointY":58.237244916166674},"width":412,"sublayerTransform":[1,0,0,0,0,1,0,0,0,0,1,0,0,0,0,1],"contentsRect":{"y":0,"x":0,"width":1,"height":1},"opacity":1,"edgeAntialiasingMask":0,"height":119,"hidden":true,"anchorPoint":{"pointX":0.5,"pointY":0.5}},"texture":"A37863128BCF3FDA3869001B69046A9A"}]}]},{"animations":[],"initialState":{"affineTransform":[1,0,0,1,0,0],"masksToBounds":false,"rotation":0,"scale":1,"position":{"pointX":480,"pointY":270},"width":960,"sublayerTransform":[1,0,0,0,0,1,0,0,0,0,1,0,0,0,0,1],"contentsRect":{"y":0,"x":0,"width":1,"height":1},"opacity":1,"edgeAntialiasingMask":251658240,"height":540,"hidden":false,"anchorPoint":{"pointX":0.5,"pointY":0.5}},"layers":[{"animations":[],"initialState":{"affineTransform":[1,0,0,1,0,0],"masksToBounds":false,"rotation":0,"scale":1,"position":{"pointX":673.12914445644287,"pointY":303.46291363333154},"width":352,"sublayerTransform":[1,0,0,0,0,1,0,0,0,0,1,0,0,0,0,1],"contentsRect":{"y":0,"x":0,"width":1,"height":1},"opacity":1,"edgeAntialiasingMask":251658240,"height":387,"hidden":false,"anchorPoint":{"pointX":0.5,"pointY":0.5}},"objectID":"50D82587-25D7-4023-9DDE-7F2FFF91A79A","layers":[{"animations":[],"layers":[],"texturedRectangle":{"singleTextureOpacity":1,"textXHeight":0.022007751937984498,"textBaseline":0.9854685485156236,"isBackgroundTexture":true,"isVerticalText":false,"textColor":[0.08235294371843338,0.08235294371843338,0.08235294371843338,1],"textureType":6},"initialState":{"affineTransform":[1,0,0,1,0,0],"masksToBounds":false,"rotation":0,"scale":1,"position":{"pointX":177.87085554355713,"pointY":196.53708636666846},"width":352,"sublayerTransform":[1,0,0,0,0,1,0,0,0,0,1,0,0,0,0,1],"contentsRect":{"y":0,"x":0,"width":1,"height":1},"opacity":1,"edgeAntialiasingMask":0,"height":387,"hidden":true,"anchorPoint":{"pointX":0.5,"pointY":0.5}},"texture":"BE0EF8AC4767274F13F1A56A0F350673"}]}]},{"animations":[],"initialState":{"affineTransform":[1,0,0,1,0,0],"masksToBounds":false,"rotation":0,"scale":1,"position":{"pointX":480,"pointY":270},"width":960,"sublayerTransform":[1,0,0,0,0,1,0,0,0,0,1,0,0,0,0,1],"contentsRect":{"y":0,"x":0,"width":1,"height":1},"opacity":1,"edgeAntialiasingMask":251658240,"height":540,"hidden":false,"anchorPoint":{"pointX":0.5,"pointY":0.5}},"layers":[{"animations":[],"initialState":{"affineTransform":[1,0,0,1,0,0],"masksToBounds":false,"rotation":0,"scale":1,"position":{"pointX":249.8005468539117,"pointY":151.78023443447321},"width":318,"sublayerTransform":[1,0,0,0,0,1,0,0,0,0,1,0,0,0,0,1],"contentsRect":{"y":0,"x":0,"width":1,"height":1},"opacity":1,"edgeAntialiasingMask":251658240,"height":60,"hidden":false,"anchorPoint":{"pointX":0.5,"pointY":0.5}},"objectID":"13480192-313A-4D7E-A537-9EBFD811BCE6","layers":[{"animations":[],"layers":[],"texturedRectangle":{"isBackgroundTexture":true,"singleTextureOpacity":1,"textureType":5,"textBaseline":0,"textXHeight":0,"isVerticalText":false},"initialState":{"affineTransform":[1,0,0,1,0,0],"masksToBounds":false,"rotation":0,"scale":1,"position":{"pointX":157.1994531460883,"pointY":28.219765565526785},"width":318,"sublayerTransform":[1,0,0,0,0,1,0,0,0,0,1,0,0,0,0,1],"contentsRect":{"y":0,"x":0,"width":1,"height":1},"opacity":1,"edgeAntialiasingMask":0,"height":60,"hidden":false,"anchorPoint":{"pointX":0.5,"pointY":0.5}},"texture":"ED77A4173F60787A84F36B76E1B1DDF4"}]}]},{"animations":[],"initialState":{"affineTransform":[1,0,0,1,0,0],"masksToBounds":false,"rotation":0,"scale":1,"position":{"pointX":480,"pointY":270},"width":960,"sublayerTransform":[1,0,0,0,0,1,0,0,0,0,1,0,0,0,0,1],"contentsRect":{"y":0,"x":0,"width":1,"height":1},"opacity":1,"edgeAntialiasingMask":251658240,"height":540,"hidden":false,"anchorPoint":{"pointX":0.5,"pointY":0.5}},"layers":[{"animations":[],"initialState":{"affineTransform":[1,0,0,1,0,0],"masksToBounds":false,"rotation":0,"scale":1,"position":{"pointX":577.52881056001388,"pointY":53.22566870121409},"width":156,"sublayerTransform":[1,0,0,0,0,1,0,0,0,0,1,0,0,0,0,1],"contentsRect":{"y":0,"x":0,"width":1,"height":1},"opacity":1,"edgeAntialiasingMask":251658240,"height":98,"hidden":false,"anchorPoint":{"pointX":0.5,"pointY":0.5}},"layers":[{"animations":[],"layers":[],"texturedRectangle":{"isBackgroundTexture":true,"singleTextureOpacity":1,"textureType":5,"textBaseline":0,"textXHeight":0,"isVerticalText":false},"initialState":{"affineTransform":[1,0,0,1,0,0],"masksToBounds":false,"rotation":0,"scale":1,"position":{"pointX":76.471189439986119,"pointY":47.77433129878591},"width":156,"sublayerTransform":[1,0,0,0,0,1,0,0,0,0,1,0,0,0,0,1],"contentsRect":{"y":0,"x":0,"width":1,"height":1},"opacity":1,"edgeAntialiasingMask":0,"height":98,"hidden":false,"anchorPoint":{"pointX":0.5,"pointY":0.5}},"texture":"0C9392F1606516E5FD8AADE86409C03B"}]}]}]}},{"effects":[{"beginTime":0,"baseLayer":{"animations":[],"initialState":{"affineTransform":[1,0,0,1,0,0],"masksToBounds":false,"rotation":0,"scale":1,"position":{"pointX":673.12914445644287,"pointY":303.46291363333154},"width":352,"sublayerTransform":[1,0,0,0,0,1,0,0,0,0,1,0,0,0,0,1],"contentsRect":{"y":0,"x":0,"width":1,"height":1},"opacity":1,"edgeAntialiasingMask":251658240,"height":387,"hidden":false,"anchorPoint":{"pointX":0.5,"pointY":0.5}},"objectID":"50D82587-25D7-4023-9DDE-7F2FFF91A79A","layers":[{"animations":[],"initialState":{"affineTransform":[1,0,0,1,0,0],"masksToBounds":false,"rotation":0,"scale":1,"position":{"pointX":-17.129144456442873,"pointY":160.03708636666846},"width":352,"sublayerTransform":[1,0,0,0,0,1,0,0,0,0,1,-0.00070015824933551967,0,0,0,1],"contentsRect":{"y":0,"x":0,"width":1,"height":1},"opacity":1,"edgeAntialiasingMask":251658240,"height":387,"hidden":false,"anchorPoint":{"pointX":-0.048662342205803615,"pointY":0.413532522911288}},"layers":[{"animations":[{"additive":false,"timeOffset":0,"beginTime":1e-100,"repeatCount":0,"fillMode":"both","duration":0.001,"autoreverses":false,"animations":[{"additive":false,"timeOffset":0,"beginTime":0,"from":{"scalar":true},"repeatCount":0,"fillMode":"both","duration":0.0001,"autoreverses":false,"property":"hidden","to":{"scalar":false},"removedOnCompletion":true},{"additive":false,"timeOffset":0,"beginTime":0.0001,"from":{"scalar":false},"repeatCount":0,"fillMode":"forwards","duration":0.00089999999999999998,"autoreverses":false,"property":"hidden","to":{"scalar":false},"removedOnCompletion":true}],"removedOnCompletion":false}],"layers":[],"texturedRectangle":{"singleTextureOpacity":1,"textXHeight":0.022007751937984498,"textBaseline":0.9854685485156236,"isBackgroundTexture":true,"isVerticalText":false,"textColor":[0.08235294371843338,0.08235294371843338,0.08235294371843338,1],"textureType":6},"initialState":{"affineTransform":[1,0,0,1,0,0],"masksToBounds":false,"rotation":0,"scale":1,"position":{"pointX":177.87085554355713,"pointY":196.53708636666846},"width":352,"sublayerTransform":[1,0,0,0,0,1,0,0,0,0,1,0,0,0,0,1],"contentsRect":{"y":0,"x":0,"width":1,"height":1},"opacity":1,"edgeAntialiasingMask":0,"height":387,"hidden":true,"anchorPoint":{"pointX":0.5,"pointY":0.5}},"texture":"BE0EF8AC4767274F13F1A56A0F350673"}]}]},"effects":[],"duration":0.001,"type":"buildIn","attributes":{"direction":0},"name":"apple:bc-appear","objectID":"50D82587-25D7-4023-9DDE-7F2FFF91A79A"}],"automaticPlay":false,"hyperlinks":[],"accessibility":[{"text":"Veeam","targetRectangle":{"y":138.07188846681692,"x":306.32321233957276,"width":59.291999999999973,"height":23}},{"text":"OpenShift\\u2028Virtualization","targetRectangle":{"y":433.87047197613163,"x":87.555826198495311,"width":152.66399999999999,"height":62}},{"text":"Google Shape;4196;p228","targetRectangle":{"y":391.9639363079732,"x":279.04858162131859,"width":145.11181640625,"height":46.586929321289062}},{"text":"Google Shape;1631;p110","targetRectangle":{"y":497.10629293573453,"x":843.40777587890625,"width":76.84375,"height":17.968749999999943}},{"text":"Hundreds of Applications","targetRectangle":{"y":229.01204255930816,"x":188.29054962154714,"width":122.10000000000002,"height":52}},{"text":"6,200 Cores","targetRectangle":{"y":307.01204255930816,"x":189.42054962154717,"width":116.22,"height":26}},{"text":"Google Shape;4194;p228","targetRectangle":{"y":386.26275508383333,"x":15.359758680235245,"width":200.32347106933594,"height":53.941417694091797}},{"text":"Google Shape;4199;p228","targetRectangle":{"y":139.67527516136397,"x":96.273144134796894,"width":121.85031890869141,"height":19.688583374023438}},{"text":"Google Shape;4203;p228","targetRectangle":{"y":4.2256687012140901,"x":499.52881056001388,"width":152.59375,"height":95.250077659522503}},{"text":"Customer Success Story ","targetRectangle":{"y":15.216771233786972,"x":38.398406126367945,"width":429.82900000000001,"height":73.5}}],"baseLayer":{"animations":[],"initialState":{"affineTransform":[1,0,0,1,0,0],"masksToBounds":false,"rotation":0,"scale":1,"position":{"pointX":480,"pointY":270},"width":960,"sublayerTransform":[1,0,0,0,0,1,0,0,0,0,1,0,0,0,0,1],"contentsRect":{"y":0,"x":0,"width":1,"height":1},"opacity":1,"edgeAntialiasingMask":251658240,"height":540,"hidden":false,"anchorPoint":{"pointX":0.5,"pointY":0.5}},"layers":[{"animations":[],"initialState":{"affineTransform":[1,0,0,1,0,0],"masksToBounds":false,"rotation":0,"scale":1,"position":{"pointX":480,"pointY":270},"width":960,"sublayerTransform":[1,0,0,0,0,1,0,0,0,0,1,0,0,0,0,1],"contentsRect":{"y":0,"x":0,"width":1,"height":1},"opacity":1,"edgeAntialiasingMask":251658240,"height":540,"hidden":false,"anchorPoint":{"pointX":0.5,"pointY":0.5}},"layers":[{"animations":[],"initialState":{"affineTransform":[1,0,0,1,0,0],"masksToBounds":false,"rotation":0,"scale":1,"position":{"pointX":480,"pointY":270},"width":960,"sublayerTransform":[1,0,0,0,0,1,0,0,0,0,1,0,0,0,0,1],"contentsRect":{"y":0,"x":0,"width":1,"height":1},"opacity":1,"edgeAntialiasingMask":251658240,"height":540,"hidden":false,"anchorPoint":{"pointX":0.5,"pointY":0.5}},"layers":[{"animations":[],"layers":[],"texturedRectangle":{"isBackgroundTexture":true,"singleTextureOpacity":1,"textureType":1,"textBaseline":0,"textXHeight":0,"isVerticalText":false},"initialState":{"affineTransform":[1,0,0,1,0,0],"masksToBounds":false,"rotation":0,"scale":1,"position":{"pointX":480,"pointY":270},"width":960,"sublayerTransform":[1,0,0,0,0,1,0,0,0,0,1,0,0,0,0,1],"contentsRect":{"y":0,"x":0,"width":1,"height":1},"opacity":1,"edgeAntialiasingMask":0,"height":540,"hidden":false,"anchorPoint":{"pointX":0.5,"pointY":0.5}},"texture":"063F32FE31288BDCCDA81E55EF79D28B"}]}]},{"animations":[],"initialState":{"affineTransform":[1,0,0,1,0,0],"masksToBounds":false,"rotation":0,"scale":1,"position":{"pointX":480,"pointY":270},"width":960,"sublayerTransform":[1,0,0,0,0,1,0,0,0,0,1,0,0,0,0,1],"contentsRect":{"y":0,"x":0,"width":1,"height":1},"opacity":1,"edgeAntialiasingMask":251658240,"height":540,"hidden":false,"anchorPoint":{"pointX":0.5,"pointY":0.5}},"layers":[{"animations":[],"initialState":{"affineTransform":[1,0,0,1,0,0],"masksToBounds":false,"rotation":0,"scale":1,"position":{"pointX":36.982873535156244,"pointY":36.007948083001907},"width":4,"sublayerTransform":[1,0,0,0,0,1,0,0,0,0,1,0,0,0,0,1],"contentsRect":{"y":0,"x":0,"width":1,"height":1},"opacity":1,"edgeAntialiasingMask":251658240,"height":72,"hidden":false,"anchorPoint":{"pointX":0.5,"pointY":0.5}},"layers":[{"animations":[],"layers":[],"texturedRectangle":{"singleTextureOpacity":1,"textXHeight":0,"shapePath":{"lineWidth":1,"flatness":0.59999999999999998,"lineCapStyle":0,"elements":[{"type":"MoveToPoint","points":[[2.3578735351562443,70.811019979132766]]},{"type":"AddLine","points":[[2.3578735351562514,1.0079480830019065]]}],"windingRule":0,"lineJoinStyle":0,"miterLimit":10},"isBackgroundTexture":true,"textBaseline":0,"isVerticalText":false,"textureType":5},"initialState":{"affineTransform":[1,0,0,1,0,0],"masksToBounds":false,"rotation":0,"scale":1,"position":{"pointX":0.017126464843755684,"pointY":34.992051916998093},"width":4,"sublayerTransform":[1,0,0,0,0,1,0,0,0,0,1,0,0,0,0,1],"contentsRect":{"y":0,"x":0,"width":1,"height":1},"opacity":1,"edgeAntialiasingMask":0,"height":72,"hidden":false,"anchorPoint":{"pointX":0.5,"pointY":0.5}},"texture":"C54F8979F117F59627802EC083318BDC"}]}]},{"animations":[],"initialState":{"affineTransform":[1,0,0,1,0,0],"masksToBounds":false,"rotation":0,"scale":1,"position":{"pointX":480,"pointY":270},"width":960,"sublayerTransform":[1,0,0,0,0,1,0,0,0,0,1,0,0,0,0,1],"contentsRect":{"y":0,"x":0,"width":1,"height":1},"opacity":1,"edgeAntialiasingMask":251658240,"height":540,"hidden":false,"anchorPoint":{"pointX":0.5,"pointY":0.5}},"layers":[{"animations":[],"initialState":{"affineTransform":[1,0,0,1,0,0],"masksToBounds":false,"rotation":0,"scale":1,"position":{"pointX":36.982244110107416,"pointY":523.04723928371163},"width":4,"sublayerTransform":[1,0,0,0,0,1,0,0,0,0,1,0,0,0,0,1],"contentsRect":{"y":0,"x":0,"width":1,"height":1},"opacity":1,"edgeAntialiasingMask":251658240,"height":38,"hidden":false,"anchorPoint":{"pointX":0.5,"pointY":0.5}},"layers":[{"animations":[],"layers":[],"texturedRectangle":{"singleTextureOpacity":1,"textXHeight":0,"shapePath":{"lineWidth":1,"flatness":0.59999999999999998,"lineCapStyle":0,"elements":[{"type":"MoveToPoint","points":[[2.3572441101074162,36.999995719729441]]},{"type":"AddLine","points":[[2.3572441101074162,1.0472392837116331]]}],"windingRule":0,"lineJoinStyle":0,"miterLimit":10},"isBackgroundTexture":true,"textBaseline":0,"isVerticalText":false,"textureType":5},"initialState":{"affineTransform":[1,0,0,1,0,0],"masksToBounds":false,"rotation":0,"scale":1,"position":{"pointX":0.017755889892583809,"pointY":17.952760716288367},"width":4,"sublayerTransform":[1,0,0,0,0,1,0,0,0,0,1,0,0,0,0,1],"contentsRect":{"y":0,"x":0,"width":1,"height":1},"opacity":1,"edgeAntialiasingMask":0,"height":38,"hidden":false,"anchorPoint":{"pointX":0.5,"pointY":0.5}},"texture":"4FC9773900971738E5F56D1D94665F05"}]}]},{"animations":[],"initialState":{"affineTransform":[1,0,0,1,0,0],"masksToBounds":false,"rotation":0,"scale":1,"position":{"pointX":480,"pointY":270},"width":960,"sublayerTransform":[1,0,0,0,0,1,0,0,0,0,1,0,0,0,0,1],"contentsRect":{"y":0,"x":0,"width":1,"height":1},"opacity":1,"edgeAntialiasingMask":251658240,"height":540,"hidden":false,"anchorPoint":{"pointX":0.5,"pointY":0.5}},"layers":[{"animations":[],"initialState":{"affineTransform":[1,0,0,1,0,0],"masksToBounds":false,"rotation":0,"scale":1,"position":{"pointX":883.40777587890625,"pointY":507.60629293573453},"width":80,"sublayerTransform":[1,0,0,0,0,1,0,0,0,0,1,0,0,0,0,1],"contentsRect":{"y":0,"x":0,"width":1,"height":1},"opacity":1,"edgeAntialiasingMask":251658240,"height":21,"hidden":false,"anchorPoint":{"pointX":0.5,"pointY":0.5}},"layers":[{"animations":[],"layers":[],"texturedRectangle":{"isBackgroundTexture":true,"singleTextureOpacity":1,"textureType":5,"textBaseline":0,"textXHeight":0,"isVerticalText":false},"initialState":{"affineTransform":[1,0,0,1,0,0],"masksToBounds":false,"rotation":0,"scale":1,"position":{"pointX":38.59222412109375,"pointY":9.3937070642654703},"width":80,"sublayerTransform":[1,0,0,0,0,1,0,0,0,0,1,0,0,0,0,1],"contentsRect":{"y":0,"x":0,"width":1,"height":1},"opacity":1,"edgeAntialiasingMask":0,"height":21,"hidden":false,"anchorPoint":{"pointX":0.5,"pointY":0.5}},"texture":"9BD4D1AA1ECF6CB5EDB3E73F5C0E10B4"}]}]},{"animations":[],"initialState":{"affineTransform":[1,0,0,1,0,0],"masksToBounds":false,"rotation":0,"scale":1,"position":{"pointX":480,"pointY":270},"width":960,"sublayerTransform":[1,0,0,0,0,1,0,0,0,0,1,0,0,0,0,1],"contentsRect":{"y":0,"x":0,"width":1,"height":1},"opacity":1,"edgeAntialiasingMask":251658240,"height":540,"hidden":false,"anchorPoint":{"pointX":0.5,"pointY":0.5}},"layers":[{"animations":[],"initialState":{"affineTransform":[1,0,0,1,0,0],"masksToBounds":false,"rotation":0,"scale":1,"position":{"pointX":242.29998121486892,"pointY":24.618346322287948},"width":427,"sublayerTransform":[1,0,0,0,0,1,0,0,0,0,1,0,0,0,0,1],"contentsRect":{"y":0,"x":0,"width":1,"height":1},"opacity":1,"edgeAntialiasingMask":251658240,"height":38,"hidden":false,"anchorPoint":{"pointX":0.5,"pointY":0.5}},"layers":[{"animations":[],"layers":[],"texturedRectangle":{"singleTextureOpacity":1,"textXHeight":0.50728947368421051,"textBaseline":0.73504600958107413,"isBackgroundTexture":true,"isVerticalText":false,"textColor":[0.93333333730697632,0,0,1],"textureType":6},"initialState":{"affineTransform":[1,0,0,1,0,0],"masksToBounds":false,"rotation":0,"scale":1,"position":{"pointX":222.70001878513108,"pointY":38.381653677712052},"width":427,"sublayerTransform":[1,0,0,0,0,1,0,0,0,0,1,0,0,0,0,1],"contentsRect":{"y":0,"x":0,"width":1,"height":1},"opacity":1,"edgeAntialiasingMask":0,"height":38,"hidden":false,"anchorPoint":{"pointX":0.5,"pointY":0.5}},"texture":"F53BF4CCEC422DA7C11AC9737828F37B"}]}]},{"animations":[],"initialState":{"affineTransform":[1,0,0,1,0,0],"masksToBounds":false,"rotation":0,"scale":1,"position":{"pointX":480,"pointY":270},"width":960,"sublayerTransform":[1,0,0,0,0,1,0,0,0,0,1,0,0,0,0,1],"contentsRect":{"y":0,"x":0,"width":1,"height":1},"opacity":1,"edgeAntialiasingMask":251658240,"height":540,"hidden":false,"anchorPoint":{"pointX":0.5,"pointY":0.5}},"layers":[{"animations":[],"initialState":{"affineTransform":[1,0,0,1,0,0],"masksToBounds":false,"rotation":0,"scale":1,"position":{"pointX":250.30062866210938,"pointY":287.33566284179688},"width":319,"sublayerTransform":[1,0,0,0,0,1,0,0,0,0,1,0,0,0,0,1],"contentsRect":{"y":0,"x":0,"width":1,"height":1},"opacity":1,"edgeAntialiasingMask":251658240,"height":170,"hidden":false,"anchorPoint":{"pointX":0.5,"pointY":0.5}},"objectID":"CF4541FC-BC8D-4CC2-BA92-0DF01097CDC6","layers":[{"animations":[],"layers":[],"texturedRectangle":{"isBackgroundTexture":true,"singleTextureOpacity":1,"textureType":5,"textBaseline":0,"textXHeight":0,"isVerticalText":false},"initialState":{"affineTransform":[1,0,0,1,0,0],"masksToBounds":false,"rotation":0,"scale":1,"position":{"pointX":156.69937133789062,"pointY":82.664337158203125},"width":319,"sublayerTransform":[1,0,0,0,0,1,0,0,0,0,1,0,0,0,0,1],"contentsRect":{"y":0,"x":0,"width":1,"height":1},"opacity":1,"edgeAntialiasingMask":0,"height":170,"hidden":false,"anchorPoint":{"pointX":0.5,"pointY":0.5}},"texture":"AD08A39BDFC84D2E30FAF14B27AD06B8"}]}]},{"animations":[],"initialState":{"affineTransform":[1,0,0,1,0,0],"masksToBounds":false,"rotation":0,"scale":1,"position":{"pointX":480,"pointY":270},"width":960,"sublayerTransform":[1,0,0,0,0,1,0,0,0,0,1,0,0,0,0,1],"contentsRect":{"y":0,"x":0,"width":1,"height":1},"opacity":1,"edgeAntialiasingMask":251658240,"height":540,"hidden":false,"anchorPoint":{"pointX":0.5,"pointY":0.5}},"layers":[{"animations":[],"initialState":{"affineTransform":[1,0,0,1,0,0],"masksToBounds":false,"rotation":0,"scale":1,"position":{"pointX":221.35975868023525,"pointY":445.76275508383333},"width":412,"sublayerTransform":[1,0,0,0,0,1,0,0,0,0,1,0,0,0,0,1],"contentsRect":{"y":0,"x":0,"width":1,"height":1},"opacity":1,"edgeAntialiasingMask":251658240,"height":119,"hidden":false,"anchorPoint":{"pointX":0.5,"pointY":0.5}},"objectID":"3EB5EB02-7863-4ED3-AF07-7C45A22F1867","layers":[{"animations":[],"layers":[],"texturedRectangle":{"isBackgroundTexture":true,"singleTextureOpacity":1,"textureType":5,"textBaseline":0,"textXHeight":0,"isVerticalText":false},"initialState":{"affineTransform":[1,0,0,1,0,0],"masksToBounds":false,"rotation":0,"scale":1,"position":{"pointX":204.64024131976475,"pointY":58.237244916166674},"width":412,"sublayerTransform":[1,0,0,0,0,1,0,0,0,0,1,0,0,0,0,1],"contentsRect":{"y":0,"x":0,"width":1,"height":1},"opacity":1,"edgeAntialiasingMask":0,"height":119,"hidden":false,"anchorPoint":{"pointX":0.5,"pointY":0.5}},"texture":"A37863128BCF3FDA3869001B69046A9A"}]}]},{"animations":[],"initialState":{"affineTransform":[1,0,0,1,0,0],"masksToBounds":false,"rotation":0,"scale":1,"position":{"pointX":480,"pointY":270},"width":960,"sublayerTransform":[1,0,0,0,0,1,0,0,0,0,1,0,0,0,0,1],"contentsRect":{"y":0,"x":0,"width":1,"height":1},"opacity":1,"edgeAntialiasingMask":251658240,"height":540,"hidden":false,"anchorPoint":{"pointX":0.5,"pointY":0.5}},"layers":[{"animations":[],"initialState":{"affineTransform":[1,0,0,1,0,0],"masksToBounds":false,"rotation":0,"scale":1,"position":{"pointX":673.12914445644287,"pointY":303.46291363333154},"width":352,"sublayerTransform":[1,0,0,0,0,1,0,0,0,0,1,0,0,0,0,1],"contentsRect":{"y":0,"x":0,"width":1,"height":1},"opacity":1,"edgeAntialiasingMask":251658240,"height":387,"hidden":false,"anchorPoint":{"pointX":0.5,"pointY":0.5}},"objectID":"50D82587-25D7-4023-9DDE-7F2FFF91A79A","layers":[{"animations":[],"layers":[],"texturedRectangle":{"singleTextureOpacity":1,"textXHeight":0.022007751937984498,"textBaseline":0.9854685485156236,"isBackgroundTexture":true,"isVerticalText":false,"textColor":[0.08235294371843338,0.08235294371843338,0.08235294371843338,1],"textureType":6},"initialState":{"affineTransform":[1,0,0,1,0,0],"masksToBounds":false,"rotation":0,"scale":1,"position":{"pointX":177.87085554355713,"pointY":196.53708636666846},"width":352,"sublayerTransform":[1,0,0,0,0,1,0,0,0,0,1,0,0,0,0,1],"contentsRect":{"y":0,"x":0,"width":1,"height":1},"opacity":1,"edgeAntialiasingMask":0,"height":387,"hidden":true,"anchorPoint":{"pointX":0.5,"pointY":0.5}},"texture":"BE0EF8AC4767274F13F1A56A0F350673"}]}]},{"animations":[],"initialState":{"affineTransform":[1,0,0,1,0,0],"masksToBounds":false,"rotation":0,"scale":1,"position":{"pointX":480,"pointY":270},"width":960,"sublayerTransform":[1,0,0,0,0,1,0,0,0,0,1,0,0,0,0,1],"contentsRect":{"y":0,"x":0,"width":1,"height":1},"opacity":1,"edgeAntialiasingMask":251658240,"height":540,"hidden":false,"anchorPoint":{"pointX":0.5,"pointY":0.5}},"layers":[{"animations":[],"initialState":{"affineTransform":[1,0,0,1,0,0],"masksToBounds":false,"rotation":0,"scale":1,"position":{"pointX":249.8005468539117,"pointY":151.78023443447321},"width":318,"sublayerTransform":[1,0,0,0,0,1,0,0,0,0,1,0,0,0,0,1],"contentsRect":{"y":0,"x":0,"width":1,"height":1},"opacity":1,"edgeAntialiasingMask":251658240,"height":60,"hidden":false,"anchorPoint":{"pointX":0.5,"pointY":0.5}},"objectID":"13480192-313A-4D7E-A537-9EBFD811BCE6","layers":[{"animations":[],"layers":[],"texturedRectangle":{"isBackgroundTexture":true,"singleTextureOpacity":1,"textureType":5,"textBaseline":0,"textXHeight":0,"isVerticalText":false},"initialState":{"affineTransform":[1,0,0,1,0,0],"masksToBounds":false,"rotation":0,"scale":1,"position":{"pointX":157.1994531460883,"pointY":28.219765565526785},"width":318,"sublayerTransform":[1,0,0,0,0,1,0,0,0,0,1,0,0,0,0,1],"contentsRect":{"y":0,"x":0,"width":1,"height":1},"opacity":1,"edgeAntialiasingMask":0,"height":60,"hidden":false,"anchorPoint":{"pointX":0.5,"pointY":0.5}},"texture":"ED77A4173F60787A84F36B76E1B1DDF4"}]}]},{"animations":[],"initialState":{"affineTransform":[1,0,0,1,0,0],"masksToBounds":false,"rotation":0,"scale":1,"position":{"pointX":480,"pointY":270},"width":960,"sublayerTransform":[1,0,0,0,0,1,0,0,0,0,1,0,0,0,0,1],"contentsRect":{"y":0,"x":0,"width":1,"height":1},"opacity":1,"edgeAntialiasingMask":251658240,"height":540,"hidden":false,"anchorPoint":{"pointX":0.5,"pointY":0.5}},"layers":[{"animations":[],"initialState":{"affineTransform":[1,0,0,1,0,0],"masksToBounds":false,"rotation":0,"scale":1,"position":{"pointX":577.52881056001388,"pointY":53.22566870121409},"width":156,"sublayerTransform":[1,0,0,0,0,1,0,0,0,0,1,0,0,0,0,1],"contentsRect":{"y":0,"x":0,"width":1,"height":1},"opacity":1,"edgeAntialiasingMask":251658240,"height":98,"hidden":false,"anchorPoint":{"pointX":0.5,"pointY":0.5}},"layers":[{"animations":[],"layers":[],"texturedRectangle":{"isBackgroundTexture":true,"singleTextureOpacity":1,"textureType":5,"textBaseline":0,"textXHeight":0,"isVerticalText":false},"initialState":{"affineTransform":[1,0,0,1,0,0],"masksToBounds":false,"rotation":0,"scale":1,"position":{"pointX":76.471189439986119,"pointY":47.77433129878591},"width":156,"sublayerTransform":[1,0,0,0,0,1,0,0,0,0,1,0,0,0,0,1],"contentsRect":{"y":0,"x":0,"width":1,"height":1},"opacity":1,"edgeAntialiasingMask":0,"height":98,"hidden":false,"anchorPoint":{"pointX":0.5,"pointY":0.5}},"texture":"0C9392F1606516E5FD8AADE86409C03B"}]}]}]}},{"effects":[{"beginTime":0,"baseLayer":{"animations":[],"initialState":{"affineTransform":[1,0,0,1,0,0],"masksToBounds":false,"rotation":0,"scale":1,"position":{"pointX":480,"pointY":270},"width":960,"sublayerTransform":[1,0,0,0,0,1,0,0,0,0,1,0,0,0,0,1],"contentsRect":{"y":0,"x":0,"width":1,"height":1},"opacity":1,"edgeAntialiasingMask":251658240,"height":540,"hidden":false,"anchorPoint":{"pointX":0.5,"pointY":0.5}},"objectID":"0","layers":[{"animations":[],"initialState":{"affineTransform":[1,0,0,1,0,0],"masksToBounds":false,"rotation":0,"scale":1,"position":{"pointX":480,"pointY":270},"width":960,"sublayerTransform":[1,0,0,0,0,1,0,0,0,0,1,-0.00070015824933551967,0,0,0,1],"contentsRect":{"y":0,"x":0,"width":1,"height":1},"opacity":1,"edgeAntialiasingMask":251658240,"height":540,"hidden":false,"anchorPoint":{"pointX":0.5,"pointY":0.5}},"layers":[{"animations":[],"layers":[],"texturedRectangle":{"isBackgroundTexture":false,"singleTextureOpacity":1,"textureType":0,"textBaseline":0,"textXHeight":0,"isVerticalText":false},"initialState":{"affineTransform":[1,0,0,1,0,0],"masksToBounds":false,"rotation":0,"scale":1,"position":{"pointX":480,"pointY":270},"width":960,"sublayerTransform":[1,0,0,0,0,1,0,0,0,0,1,0,0,0,0,1],"contentsRect":{"y":0,"x":0,"width":1,"height":1},"opacity":1,"edgeAntialiasingMask":0,"height":540,"hidden":false,"anchorPoint":{"pointX":0.5,"pointY":0.5}},"texture":"376E86731AE1B52F73AC6D82B256BB51"},{"animations":[{"additive":false,"timeOffset":0,"beginTime":0,"from":{"scalar":false},"repeatCount":0,"fillMode":"both","duration":0.001,"autoreverses":false,"property":"hidden","to":{"scalar":true},"removedOnCompletion":false}],"layers":[],"texturedRectangle":{"isBackgroundTexture":false,"singleTextureOpacity":1,"textureType":0,"textBaseline":0,"textXHeight":0,"isVerticalText":false},"initialState":{"affineTransform":[1,0,0,1,0,0],"masksToBounds":false,"rotation":0,"scale":1,"position":{"pointX":480,"pointY":270},"width":960,"sublayerTransform":[1,0,0,0,0,1,0,0,0,0,1,0,0,0,0,1],"contentsRect":{"y":0,"x":0,"width":1,"height":1},"opacity":1,"edgeAntialiasingMask":0,"height":540,"hidden":false,"anchorPoint":{"pointX":0.5,"pointY":0.5}},"texture":"EA5059272FA6B0B485E2B01493C2E69C"}]}]},"effects":[],"duration":0.001,"type":"transition","attributes":{"direction":0},"name":"none","objectID":"0"}],"automaticPlay":false,"hyperlinks":[],"accessibility":[{"text":"Veeam","targetRectangle":{"y":138.07188846681692,"x":306.32321233957276,"width":59.291999999999973,"height":23}},{"text":"OpenShift\\u2028Virtualization","targetRectangle":{"y":433.87047197613163,"x":87.555826198495311,"width":152.66399999999999,"height":62}},{"text":"Google Shape;4196;p228","targetRectangle":{"y":391.9639363079732,"x":279.04858162131859,"width":145.11181640625,"height":46.586929321289062}},{"text":"WHY TRILIO? ","targetRectangle":{"y":113.56133878324914,"x":664.58236566882988,"width":106.65800000000013,"height":22}},{"text":"EASE OF USE","targetRectangle":{"y":135.56133878324914,"x":500.72756960636048,"width":108.90200000000004,"height":28}},{"text":"Integrated = OCP User Interface *","targetRectangle":{"y":163.56133878324914,"x":527.72756960636048,"width":253.92899999999997,"height":28}},{"text":"Automated = Ansible Playbooks \/ ACM","targetRectangle":{"y":191.56133878324914,"x":527.72756960636048,"width":291.87300000000005,"height":28}},{"text":"Certified = Operator (Fast Deployment)","targetRectangle":{"y":219.56133878324914,"x":527.72756960636048,"width":298.48599999999999,"height":28}},{"text":"UNMATCHED RECOVERY","targetRectangle":{"y":275.56133878324914,"x":500.72756960636048,"width":201.85799999999995,"height":28}},{"text":"File Level Recovery *","targetRectangle":{"y":303.56133878324914,"x":527.72756960636048,"width":156.63799999999992,"height":28}},{"text":"Disaster Recovery w\/ Continuous Restore *","targetRectangle":{"y":331.56133878324914,"x":527.72756960636048,"width":321.99699999999996,"height":28}},{"text":"Operator Protection & Rollback *","targetRectangle":{"y":359.56133878324914,"x":527.72756960636048,"width":245.13999999999999,"height":28}},{"text":"FUTURE PROOFED","targetRectangle":{"y":415.56133878324914,"x":500.72756960636048,"width":154.76800000000003,"height":28}},{"text":"No Lock-in; Non-proprietary Format *","targetRectangle":{"y":443.56133878324914,"x":527.72756960636048,"width":282.28499999999985,"height":28}},{"text":"Ability to Migrate from other Distros","targetRectangle":{"y":471.56133878324914,"x":527.72756960636048,"width":267.529,"height":28}},{"text":"Google Shape;1631;p110","targetRectangle":{"y":497.10629293573453,"x":843.40777587890625,"width":76.84375,"height":17.968749999999943}},{"text":"Hundreds of Applications","targetRectangle":{"y":229.01204255930816,"x":188.29054962154714,"width":122.10000000000002,"height":52}},{"text":"6,200 Cores","targetRectangle":{"y":307.01204255930816,"x":189.42054962154717,"width":116.22,"height":26}},{"text":"Google Shape;4194;p228","targetRectangle":{"y":386.26275508383333,"x":15.359758680235245,"width":200.32347106933594,"height":53.941417694091797}},{"text":"Google Shape;4199;p228","targetRectangle":{"y":139.67527516136397,"x":96.273144134796894,"width":121.85031890869141,"height":19.688583374023438}},{"text":"Google Shape;4203;p228","targetRectangle":{"y":4.2256687012140901,"x":499.52881056001388,"width":152.59375,"height":95.250077659522503}},{"text":"Customer Success Story ","targetRectangle":{"y":15.216771233786972,"x":38.398406126367945,"width":429.82900000000001,"height":73.5}}],"baseLayer":{"animations":[],"initialState":{"affineTransform":[1,0,0,1,0,0],"masksToBounds":false,"rotation":0,"scale":1,"position":{"pointX":480,"pointY":270},"width":960,"sublayerTransform":[1,0,0,0,0,1,0,0,0,0,1,0,0,0,0,1],"contentsRect":{"y":0,"x":0,"width":1,"height":1},"opacity":1,"edgeAntialiasingMask":251658240,"height":540,"hidden":false,"anchorPoint":{"pointX":0.5,"pointY":0.5}},"objectID":"0","layers":[{"animations":[],"initialState":{"affineTransform":[1,0,0,1,0,0],"masksToBounds":false,"rotation":0,"scale":1,"position":{"pointX":480,"pointY":270},"width":960,"sublayerTransform":[1,0,0,0,0,1,0,0,0,0,1,-0.00070015824933551967,0,0,0,1],"contentsRect":{"y":0,"x":0,"width":1,"height":1},"opacity":1,"edgeAntialiasingMask":251658240,"height":540,"hidden":false,"anchorPoint":{"pointX":0.5,"pointY":0.5}},"layers":[{"animations":[],"layers":[],"texturedRectangle":{"isBackgroundTexture":false,"singleTextureOpacity":1,"textureType":0,"textBaseline":0,"textXHeight":0,"isVerticalText":false},"initialState":{"affineTransform":[1,0,0,1,0,0],"masksToBounds":false,"rotation":0,"scale":1,"position":{"pointX":480,"pointY":270},"width":960,"sublayerTransform":[1,0,0,0,0,1,0,0,0,0,1,0,0,0,0,1],"contentsRect":{"y":0,"x":0,"width":1,"height":1},"opacity":1,"edgeAntialiasingMask":0,"height":540,"hidden":false,"anchorPoint":{"pointX":0.5,"pointY":0.5}},"texture":"EA5059272FA6B0B485E2B01493C2E69C"}]}]}}]}